package com.sohu.httpserver;

import org.apache.http.HttpServerConnection;
import org.apache.http.protocol.HttpService;

class c extends Thread
{
  private final HttpService a;
  private final HttpServerConnection b;

  public c(HttpService paramHttpService, HttpServerConnection paramHttpServerConnection)
  {
    this.a = paramHttpService;
    this.b = paramHttpServerConnection;
  }

  // ERROR //
  public void run()
  {
    // Byte code:
    //   0: ldc 26
    //   2: invokestatic 31	com/sohu/upload/a/a:a	(Ljava/lang/String;)V
    //   5: new 33	org/apache/http/protocol/BasicHttpContext
    //   8: dup
    //   9: aconst_null
    //   10: invokespecial 36	org/apache/http/protocol/BasicHttpContext:<init>	(Lorg/apache/http/protocol/HttpContext;)V
    //   13: astore_1
    //   14: invokestatic 40	java/lang/Thread:interrupted	()Z
    //   17: ifne +47 -> 64
    //   20: aload_0
    //   21: getfield 17	com/sohu/httpserver/c:b	Lorg/apache/http/HttpServerConnection;
    //   24: invokeinterface 45 1 0
    //   29: ifeq +35 -> 64
    //   32: aload_0
    //   33: getfield 15	com/sohu/httpserver/c:a	Lorg/apache/http/protocol/HttpService;
    //   36: aload_0
    //   37: getfield 17	com/sohu/httpserver/c:b	Lorg/apache/http/HttpServerConnection;
    //   40: aload_1
    //   41: invokevirtual 51	org/apache/http/protocol/HttpService:handleRequest	(Lorg/apache/http/HttpServerConnection;Lorg/apache/http/protocol/HttpContext;)V
    //   44: goto -30 -> 14
    //   47: astore 8
    //   49: ldc 53
    //   51: invokestatic 55	com/sohu/upload/a/a:b	(Ljava/lang/String;)V
    //   54: aload_0
    //   55: getfield 17	com/sohu/httpserver/c:b	Lorg/apache/http/HttpServerConnection;
    //   58: invokeinterface 58 1 0
    //   63: return
    //   64: aload_0
    //   65: getfield 17	com/sohu/httpserver/c:b	Lorg/apache/http/HttpServerConnection;
    //   68: invokeinterface 58 1 0
    //   73: return
    //   74: astore 10
    //   76: return
    //   77: astore 6
    //   79: new 60	java/lang/StringBuilder
    //   82: dup
    //   83: invokespecial 61	java/lang/StringBuilder:<init>	()V
    //   86: ldc 63
    //   88: invokevirtual 67	java/lang/StringBuilder:append	(Ljava/lang/String;)Ljava/lang/StringBuilder;
    //   91: aload 6
    //   93: invokevirtual 71	java/io/IOException:getMessage	()Ljava/lang/String;
    //   96: invokevirtual 67	java/lang/StringBuilder:append	(Ljava/lang/String;)Ljava/lang/StringBuilder;
    //   99: invokevirtual 74	java/lang/StringBuilder:toString	()Ljava/lang/String;
    //   102: invokestatic 55	com/sohu/upload/a/a:b	(Ljava/lang/String;)V
    //   105: aload_0
    //   106: getfield 17	com/sohu/httpserver/c:b	Lorg/apache/http/HttpServerConnection;
    //   109: invokeinterface 58 1 0
    //   114: return
    //   115: astore 7
    //   117: return
    //   118: astore 4
    //   120: new 60	java/lang/StringBuilder
    //   123: dup
    //   124: invokespecial 61	java/lang/StringBuilder:<init>	()V
    //   127: ldc 76
    //   129: invokevirtual 67	java/lang/StringBuilder:append	(Ljava/lang/String;)Ljava/lang/StringBuilder;
    //   132: aload 4
    //   134: invokevirtual 77	org/apache/http/HttpException:getMessage	()Ljava/lang/String;
    //   137: invokevirtual 67	java/lang/StringBuilder:append	(Ljava/lang/String;)Ljava/lang/StringBuilder;
    //   140: invokevirtual 74	java/lang/StringBuilder:toString	()Ljava/lang/String;
    //   143: invokestatic 55	com/sohu/upload/a/a:b	(Ljava/lang/String;)V
    //   146: aload_0
    //   147: getfield 17	com/sohu/httpserver/c:b	Lorg/apache/http/HttpServerConnection;
    //   150: invokeinterface 58 1 0
    //   155: return
    //   156: astore 5
    //   158: return
    //   159: astore_2
    //   160: aload_0
    //   161: getfield 17	com/sohu/httpserver/c:b	Lorg/apache/http/HttpServerConnection;
    //   164: invokeinterface 58 1 0
    //   169: aload_2
    //   170: athrow
    //   171: astore_3
    //   172: goto -3 -> 169
    //   175: astore 9
    //   177: return
    //
    // Exception table:
    //   from	to	target	type
    //   14	44	47	org/apache/http/ConnectionClosedException
    //   64	73	74	java/io/IOException
    //   14	44	77	java/io/IOException
    //   105	114	115	java/io/IOException
    //   14	44	118	org/apache/http/HttpException
    //   146	155	156	java/io/IOException
    //   14	44	159	finally
    //   49	54	159	finally
    //   79	105	159	finally
    //   120	146	159	finally
    //   160	169	171	java/io/IOException
    //   54	63	175	java/io/IOException
  }
}

/* Location:           C:\Users\THX\Desktop\aa\aa\反编译工具包\out\classes_dex2jar.jar
 * Qualified Name:     com.sohu.httpserver.c
 * JD-Core Version:    0.6.2
 */