package com.sohu.app.ads.sdk.f;

public class a
{
  private static a a = new a();

  public static a a()
  {
    return a;
  }

  // ERROR //
  public java.io.InputStream a(java.lang.String paramString1, java.lang.String paramString2)
  {
    // Byte code:
    //   0: aload_2
    //   1: invokestatic 27	com/sohu/app/ads/sdk/f/d:a	(Ljava/lang/String;)Z
    //   4: ifeq +219 -> 223
    //   7: new 29	java/lang/StringBuilder
    //   10: dup
    //   11: invokespecial 30	java/lang/StringBuilder:<init>	()V
    //   14: aload_1
    //   15: invokevirtual 34	java/lang/StringBuilder:append	(Ljava/lang/String;)Ljava/lang/StringBuilder;
    //   18: ldc 36
    //   20: invokevirtual 34	java/lang/StringBuilder:append	(Ljava/lang/String;)Ljava/lang/StringBuilder;
    //   23: aload_2
    //   24: invokevirtual 34	java/lang/StringBuilder:append	(Ljava/lang/String;)Ljava/lang/StringBuilder;
    //   27: invokevirtual 40	java/lang/StringBuilder:toString	()Ljava/lang/String;
    //   30: ldc 42
    //   32: ldc 44
    //   34: invokevirtual 50	java/lang/String:replace	(Ljava/lang/CharSequence;Ljava/lang/CharSequence;)Ljava/lang/String;
    //   37: astore_3
    //   38: new 29	java/lang/StringBuilder
    //   41: dup
    //   42: invokespecial 30	java/lang/StringBuilder:<init>	()V
    //   45: ldc 52
    //   47: invokevirtual 34	java/lang/StringBuilder:append	(Ljava/lang/String;)Ljava/lang/StringBuilder;
    //   50: aload_3
    //   51: invokevirtual 34	java/lang/StringBuilder:append	(Ljava/lang/String;)Ljava/lang/StringBuilder;
    //   54: invokevirtual 40	java/lang/StringBuilder:toString	()Ljava/lang/String;
    //   57: invokestatic 57	com/sohu/app/ads/sdk/c/a:a	(Ljava/lang/String;)V
    //   60: aload_3
    //   61: ldc 59
    //   63: invokevirtual 63	java/lang/String:contains	(Ljava/lang/CharSequence;)Z
    //   66: ifeq +55 -> 121
    //   69: aload_3
    //   70: ldc 65
    //   72: invokevirtual 63	java/lang/String:contains	(Ljava/lang/CharSequence;)Z
    //   75: ifne +46 -> 121
    //   78: ldc 67
    //   80: new 29	java/lang/StringBuilder
    //   83: dup
    //   84: invokespecial 30	java/lang/StringBuilder:<init>	()V
    //   87: new 69	java/util/Date
    //   90: dup
    //   91: invokespecial 70	java/util/Date:<init>	()V
    //   94: invokevirtual 73	java/util/Date:toLocaleString	()Ljava/lang/String;
    //   97: invokevirtual 34	java/lang/StringBuilder:append	(Ljava/lang/String;)Ljava/lang/StringBuilder;
    //   100: ldc 75
    //   102: invokevirtual 34	java/lang/StringBuilder:append	(Ljava/lang/String;)Ljava/lang/StringBuilder;
    //   105: invokevirtual 40	java/lang/StringBuilder:toString	()Ljava/lang/String;
    //   108: invokestatic 78	com/sohu/app/ads/sdk/c/a:a	(Ljava/lang/String;Ljava/lang/String;)V
    //   111: invokestatic 84	com/sohu/mobile/a/a/e:c	()Lcom/sohu/mobile/a/a/d;
    //   114: ldc 86
    //   116: invokeinterface 89 2 0
    //   121: new 91	org/apache/http/client/methods/HttpGet
    //   124: dup
    //   125: aload_3
    //   126: invokespecial 93	org/apache/http/client/methods/HttpGet:<init>	(Ljava/lang/String;)V
    //   129: astore 4
    //   131: aload 4
    //   133: invokevirtual 97	org/apache/http/client/methods/HttpGet:getParams	()Lorg/apache/http/params/HttpParams;
    //   136: astore 5
    //   138: aload 5
    //   140: sipush 3000
    //   143: invokestatic 103	org/apache/http/params/HttpConnectionParams:setConnectionTimeout	(Lorg/apache/http/params/HttpParams;I)V
    //   146: aload 5
    //   148: sipush 3000
    //   151: invokestatic 106	org/apache/http/params/HttpConnectionParams:setSoTimeout	(Lorg/apache/http/params/HttpParams;I)V
    //   154: new 108	org/apache/http/impl/client/DefaultHttpClient
    //   157: dup
    //   158: invokespecial 109	org/apache/http/impl/client/DefaultHttpClient:<init>	()V
    //   161: astore 6
    //   163: ldc 111
    //   165: invokestatic 57	com/sohu/app/ads/sdk/c/a:a	(Ljava/lang/String;)V
    //   168: aload 6
    //   170: aload 4
    //   172: invokeinterface 117 2 0
    //   177: astore 8
    //   179: ldc 119
    //   181: invokestatic 57	com/sohu/app/ads/sdk/c/a:a	(Ljava/lang/String;)V
    //   184: aload 8
    //   186: invokeinterface 125 1 0
    //   191: invokeinterface 131 1 0
    //   196: istore 9
    //   198: iload 9
    //   200: sipush 200
    //   203: if_icmpne +116 -> 319
    //   206: aload 8
    //   208: invokeinterface 135 1 0
    //   213: invokeinterface 141 1 0
    //   218: astore 12
    //   220: aload 12
    //   222: areturn
    //   223: aload_1
    //   224: ldc 42
    //   226: ldc 44
    //   228: invokevirtual 50	java/lang/String:replace	(Ljava/lang/CharSequence;Ljava/lang/CharSequence;)Ljava/lang/String;
    //   231: astore_3
    //   232: goto -194 -> 38
    //   235: astore 7
    //   237: aload_3
    //   238: ldc 59
    //   240: invokevirtual 63	java/lang/String:contains	(Ljava/lang/CharSequence;)Z
    //   243: ifeq +55 -> 298
    //   246: aload_3
    //   247: ldc 65
    //   249: invokevirtual 63	java/lang/String:contains	(Ljava/lang/CharSequence;)Z
    //   252: ifne +46 -> 298
    //   255: ldc 67
    //   257: new 29	java/lang/StringBuilder
    //   260: dup
    //   261: invokespecial 30	java/lang/StringBuilder:<init>	()V
    //   264: new 69	java/util/Date
    //   267: dup
    //   268: invokespecial 70	java/util/Date:<init>	()V
    //   271: invokevirtual 73	java/util/Date:toLocaleString	()Ljava/lang/String;
    //   274: invokevirtual 34	java/lang/StringBuilder:append	(Ljava/lang/String;)Ljava/lang/StringBuilder;
    //   277: ldc 75
    //   279: invokevirtual 34	java/lang/StringBuilder:append	(Ljava/lang/String;)Ljava/lang/StringBuilder;
    //   282: invokevirtual 40	java/lang/StringBuilder:toString	()Ljava/lang/String;
    //   285: invokestatic 78	com/sohu/app/ads/sdk/c/a:a	(Ljava/lang/String;Ljava/lang/String;)V
    //   288: invokestatic 84	com/sohu/mobile/a/a/e:c	()Lcom/sohu/mobile/a/a/d;
    //   291: ldc 143
    //   293: invokeinterface 89 2 0
    //   298: aconst_null
    //   299: areturn
    //   300: astore 11
    //   302: aload 11
    //   304: invokevirtual 146	java/lang/IllegalStateException:printStackTrace	()V
    //   307: aconst_null
    //   308: areturn
    //   309: astore 10
    //   311: aload 10
    //   313: invokevirtual 147	java/io/IOException:printStackTrace	()V
    //   316: goto -9 -> 307
    //   319: iload 9
    //   321: sipush 400
    //   324: if_icmplt -17 -> 307
    //   327: aload_3
    //   328: ldc 59
    //   330: invokevirtual 63	java/lang/String:contains	(Ljava/lang/CharSequence;)Z
    //   333: ifeq -26 -> 307
    //   336: aload_3
    //   337: ldc 65
    //   339: invokevirtual 63	java/lang/String:contains	(Ljava/lang/CharSequence;)Z
    //   342: ifne -35 -> 307
    //   345: ldc 67
    //   347: new 29	java/lang/StringBuilder
    //   350: dup
    //   351: invokespecial 30	java/lang/StringBuilder:<init>	()V
    //   354: new 69	java/util/Date
    //   357: dup
    //   358: invokespecial 70	java/util/Date:<init>	()V
    //   361: invokevirtual 73	java/util/Date:toLocaleString	()Ljava/lang/String;
    //   364: invokevirtual 34	java/lang/StringBuilder:append	(Ljava/lang/String;)Ljava/lang/StringBuilder;
    //   367: ldc 75
    //   369: invokevirtual 34	java/lang/StringBuilder:append	(Ljava/lang/String;)Ljava/lang/StringBuilder;
    //   372: invokevirtual 40	java/lang/StringBuilder:toString	()Ljava/lang/String;
    //   375: invokestatic 78	com/sohu/app/ads/sdk/c/a:a	(Ljava/lang/String;Ljava/lang/String;)V
    //   378: invokestatic 84	com/sohu/mobile/a/a/e:c	()Lcom/sohu/mobile/a/a/d;
    //   381: ldc 149
    //   383: invokeinterface 89 2 0
    //   388: goto -81 -> 307
    //
    // Exception table:
    //   from	to	target	type
    //   168	179	235	java/lang/Exception
    //   206	220	300	java/lang/IllegalStateException
    //   206	220	309	java/io/IOException
  }

  // ERROR //
  public boolean a(java.lang.String paramString1, java.io.File paramFile, java.lang.String paramString2)
  {
    // Byte code:
    //   0: getstatic 13	com/sohu/app/ads/sdk/f/a:a	Lcom/sohu/app/ads/sdk/f/a;
    //   3: astore 4
    //   5: aload 4
    //   7: monitorenter
    //   8: invokestatic 154	com/sohu/app/ads/sdk/f/d:e	()Z
    //   11: ifne +8 -> 19
    //   14: aload 4
    //   16: monitorexit
    //   17: iconst_0
    //   18: ireturn
    //   19: aconst_null
    //   20: astore 6
    //   22: aconst_null
    //   23: astore 7
    //   25: new 29	java/lang/StringBuilder
    //   28: dup
    //   29: invokespecial 30	java/lang/StringBuilder:<init>	()V
    //   32: ldc 156
    //   34: invokevirtual 34	java/lang/StringBuilder:append	(Ljava/lang/String;)Ljava/lang/StringBuilder;
    //   37: aload_1
    //   38: invokevirtual 34	java/lang/StringBuilder:append	(Ljava/lang/String;)Ljava/lang/StringBuilder;
    //   41: invokevirtual 40	java/lang/StringBuilder:toString	()Ljava/lang/String;
    //   44: invokestatic 57	com/sohu/app/ads/sdk/c/a:a	(Ljava/lang/String;)V
    //   47: new 158	java/net/URL
    //   50: dup
    //   51: aload_1
    //   52: invokespecial 159	java/net/URL:<init>	(Ljava/lang/String;)V
    //   55: invokevirtual 163	java/net/URL:openConnection	()Ljava/net/URLConnection;
    //   58: checkcast 165	java/net/HttpURLConnection
    //   61: astore 14
    //   63: aload 14
    //   65: iconst_0
    //   66: invokevirtual 169	java/net/HttpURLConnection:setInstanceFollowRedirects	(Z)V
    //   69: aload 14
    //   71: sipush 5000
    //   74: invokevirtual 173	java/net/HttpURLConnection:setConnectTimeout	(I)V
    //   77: aload 14
    //   79: ldc 175
    //   81: invokevirtual 178	java/net/HttpURLConnection:setRequestMethod	(Ljava/lang/String;)V
    //   84: aload 14
    //   86: ldc 180
    //   88: ldc 182
    //   90: invokevirtual 185	java/net/HttpURLConnection:setRequestProperty	(Ljava/lang/String;Ljava/lang/String;)V
    //   93: aload 14
    //   95: ldc 187
    //   97: ldc 189
    //   99: invokevirtual 185	java/net/HttpURLConnection:setRequestProperty	(Ljava/lang/String;Ljava/lang/String;)V
    //   102: aload 14
    //   104: ldc 191
    //   106: ldc 193
    //   108: invokevirtual 185	java/net/HttpURLConnection:setRequestProperty	(Ljava/lang/String;Ljava/lang/String;)V
    //   111: aload 14
    //   113: ldc 195
    //   115: ldc 197
    //   117: invokevirtual 185	java/net/HttpURLConnection:setRequestProperty	(Ljava/lang/String;Ljava/lang/String;)V
    //   120: aload 14
    //   122: ldc 199
    //   124: ldc 201
    //   126: invokevirtual 185	java/net/HttpURLConnection:setRequestProperty	(Ljava/lang/String;Ljava/lang/String;)V
    //   129: aload 14
    //   131: invokevirtual 204	java/net/HttpURLConnection:getContentLength	()I
    //   134: istore 15
    //   136: aload 14
    //   138: invokevirtual 207	java/net/HttpURLConnection:getResponseCode	()I
    //   141: istore 16
    //   143: new 29	java/lang/StringBuilder
    //   146: dup
    //   147: invokespecial 30	java/lang/StringBuilder:<init>	()V
    //   150: ldc 209
    //   152: invokevirtual 34	java/lang/StringBuilder:append	(Ljava/lang/String;)Ljava/lang/StringBuilder;
    //   155: iload 15
    //   157: invokevirtual 212	java/lang/StringBuilder:append	(I)Ljava/lang/StringBuilder;
    //   160: invokevirtual 40	java/lang/StringBuilder:toString	()Ljava/lang/String;
    //   163: invokestatic 57	com/sohu/app/ads/sdk/c/a:a	(Ljava/lang/String;)V
    //   166: new 29	java/lang/StringBuilder
    //   169: dup
    //   170: invokespecial 30	java/lang/StringBuilder:<init>	()V
    //   173: ldc 214
    //   175: invokevirtual 34	java/lang/StringBuilder:append	(Ljava/lang/String;)Ljava/lang/StringBuilder;
    //   178: iload 16
    //   180: invokevirtual 212	java/lang/StringBuilder:append	(I)Ljava/lang/StringBuilder;
    //   183: invokevirtual 40	java/lang/StringBuilder:toString	()Ljava/lang/String;
    //   186: invokestatic 57	com/sohu/app/ads/sdk/c/a:a	(Ljava/lang/String;)V
    //   189: iload 16
    //   191: sipush 301
    //   194: if_icmpeq +11 -> 205
    //   197: iload 16
    //   199: sipush 302
    //   202: if_icmpne +95 -> 297
    //   205: aload 14
    //   207: ldc 216
    //   209: invokevirtual 220	java/net/HttpURLConnection:getHeaderField	(Ljava/lang/String;)Ljava/lang/String;
    //   212: astore 17
    //   214: new 29	java/lang/StringBuilder
    //   217: dup
    //   218: invokespecial 30	java/lang/StringBuilder:<init>	()V
    //   221: ldc 222
    //   223: invokevirtual 34	java/lang/StringBuilder:append	(Ljava/lang/String;)Ljava/lang/StringBuilder;
    //   226: aload 17
    //   228: invokevirtual 34	java/lang/StringBuilder:append	(Ljava/lang/String;)Ljava/lang/StringBuilder;
    //   231: invokevirtual 40	java/lang/StringBuilder:toString	()Ljava/lang/String;
    //   234: invokestatic 57	com/sohu/app/ads/sdk/c/a:a	(Ljava/lang/String;)V
    //   237: aload_0
    //   238: aload 17
    //   240: aload_2
    //   241: aload_3
    //   242: invokevirtual 224	com/sohu/app/ads/sdk/f/a:a	(Ljava/lang/String;Ljava/io/File;Ljava/lang/String;)Z
    //   245: istore 18
    //   247: iconst_0
    //   248: ifeq +7 -> 255
    //   251: aconst_null
    //   252: invokevirtual 229	java/io/InputStream:close	()V
    //   255: iconst_0
    //   256: ifeq +7 -> 263
    //   259: aconst_null
    //   260: invokevirtual 232	java/io/FileOutputStream:close	()V
    //   263: aload 4
    //   265: monitorexit
    //   266: iload 18
    //   268: ireturn
    //   269: astore 5
    //   271: aload 4
    //   273: monitorexit
    //   274: aload 5
    //   276: athrow
    //   277: astore 20
    //   279: aload 20
    //   281: invokevirtual 147	java/io/IOException:printStackTrace	()V
    //   284: goto -29 -> 255
    //   287: astore 19
    //   289: aload 19
    //   291: invokevirtual 147	java/io/IOException:printStackTrace	()V
    //   294: goto -31 -> 263
    //   297: iload 15
    //   299: iconst_m1
    //   300: if_icmpne +44 -> 344
    //   303: iconst_0
    //   304: ifeq +7 -> 311
    //   307: aconst_null
    //   308: invokevirtual 229	java/io/InputStream:close	()V
    //   311: iconst_0
    //   312: ifeq +7 -> 319
    //   315: aconst_null
    //   316: invokevirtual 232	java/io/FileOutputStream:close	()V
    //   319: aload 4
    //   321: monitorexit
    //   322: iconst_0
    //   323: ireturn
    //   324: astore 33
    //   326: aload 33
    //   328: invokevirtual 147	java/io/IOException:printStackTrace	()V
    //   331: goto -20 -> 311
    //   334: astore 32
    //   336: aload 32
    //   338: invokevirtual 147	java/io/IOException:printStackTrace	()V
    //   341: goto -22 -> 319
    //   344: new 234	java/io/File
    //   347: dup
    //   348: aload_2
    //   349: aload_3
    //   350: invokespecial 237	java/io/File:<init>	(Ljava/io/File;Ljava/lang/String;)V
    //   353: astore 21
    //   355: aload 21
    //   357: invokevirtual 240	java/io/File:exists	()Z
    //   360: istore 22
    //   362: aconst_null
    //   363: astore 7
    //   365: aconst_null
    //   366: astore 6
    //   368: iload 22
    //   370: ifeq +67 -> 437
    //   373: aload 21
    //   375: invokevirtual 244	java/io/File:length	()J
    //   378: iload 15
    //   380: i2l
    //   381: lcmp
    //   382: ifne +49 -> 431
    //   385: ldc 246
    //   387: invokestatic 57	com/sohu/app/ads/sdk/c/a:a	(Ljava/lang/String;)V
    //   390: iconst_0
    //   391: ifeq +7 -> 398
    //   394: aconst_null
    //   395: invokevirtual 229	java/io/InputStream:close	()V
    //   398: iconst_0
    //   399: ifeq +7 -> 406
    //   402: aconst_null
    //   403: invokevirtual 232	java/io/FileOutputStream:close	()V
    //   406: aload 4
    //   408: monitorexit
    //   409: iconst_1
    //   410: ireturn
    //   411: astore 31
    //   413: aload 31
    //   415: invokevirtual 147	java/io/IOException:printStackTrace	()V
    //   418: goto -20 -> 398
    //   421: astore 30
    //   423: aload 30
    //   425: invokevirtual 147	java/io/IOException:printStackTrace	()V
    //   428: goto -22 -> 406
    //   431: aload 21
    //   433: invokevirtual 249	java/io/File:delete	()Z
    //   436: pop
    //   437: aload 14
    //   439: invokevirtual 252	java/net/HttpURLConnection:getInputStream	()Ljava/io/InputStream;
    //   442: astore 24
    //   444: sipush 1024
    //   447: newarray byte
    //   449: astore 25
    //   451: new 231	java/io/FileOutputStream
    //   454: dup
    //   455: aload 21
    //   457: invokespecial 255	java/io/FileOutputStream:<init>	(Ljava/io/File;)V
    //   460: astore 26
    //   462: aload 24
    //   464: aload 25
    //   466: iconst_0
    //   467: sipush 1024
    //   470: invokevirtual 259	java/io/InputStream:read	([BII)I
    //   473: istore 27
    //   475: iload 27
    //   477: iconst_m1
    //   478: if_icmpeq +56 -> 534
    //   481: aload 26
    //   483: aload 25
    //   485: iconst_0
    //   486: iload 27
    //   488: invokevirtual 263	java/io/FileOutputStream:write	([BII)V
    //   491: goto -29 -> 462
    //   494: astore 8
    //   496: aload 26
    //   498: astore 7
    //   500: aload 24
    //   502: astore 6
    //   504: aload 8
    //   506: invokevirtual 264	java/lang/Exception:printStackTrace	()V
    //   509: aload 6
    //   511: ifnull +8 -> 519
    //   514: aload 6
    //   516: invokevirtual 229	java/io/InputStream:close	()V
    //   519: aload 7
    //   521: ifnull +8 -> 529
    //   524: aload 7
    //   526: invokevirtual 232	java/io/FileOutputStream:close	()V
    //   529: aload 4
    //   531: monitorexit
    //   532: iconst_0
    //   533: ireturn
    //   534: aload 26
    //   536: invokevirtual 267	java/io/FileOutputStream:flush	()V
    //   539: aload 26
    //   541: invokevirtual 232	java/io/FileOutputStream:close	()V
    //   544: aload 24
    //   546: invokevirtual 229	java/io/InputStream:close	()V
    //   549: aload 24
    //   551: ifnull +8 -> 559
    //   554: aload 24
    //   556: invokevirtual 229	java/io/InputStream:close	()V
    //   559: aload 26
    //   561: ifnull +8 -> 569
    //   564: aload 26
    //   566: invokevirtual 232	java/io/FileOutputStream:close	()V
    //   569: aload 4
    //   571: monitorexit
    //   572: iconst_1
    //   573: ireturn
    //   574: astore 29
    //   576: aload 29
    //   578: invokevirtual 147	java/io/IOException:printStackTrace	()V
    //   581: goto -22 -> 559
    //   584: astore 28
    //   586: aload 28
    //   588: invokevirtual 147	java/io/IOException:printStackTrace	()V
    //   591: goto -22 -> 569
    //   594: astore 13
    //   596: aload 13
    //   598: invokevirtual 147	java/io/IOException:printStackTrace	()V
    //   601: goto -82 -> 519
    //   604: astore 12
    //   606: aload 12
    //   608: invokevirtual 147	java/io/IOException:printStackTrace	()V
    //   611: goto -82 -> 529
    //   614: astore 9
    //   616: aload 6
    //   618: ifnull +8 -> 626
    //   621: aload 6
    //   623: invokevirtual 229	java/io/InputStream:close	()V
    //   626: aload 7
    //   628: ifnull +8 -> 636
    //   631: aload 7
    //   633: invokevirtual 232	java/io/FileOutputStream:close	()V
    //   636: aload 9
    //   638: athrow
    //   639: astore 11
    //   641: aload 11
    //   643: invokevirtual 147	java/io/IOException:printStackTrace	()V
    //   646: goto -20 -> 626
    //   649: astore 10
    //   651: aload 10
    //   653: invokevirtual 147	java/io/IOException:printStackTrace	()V
    //   656: goto -20 -> 636
    //   659: astore 9
    //   661: aload 24
    //   663: astore 6
    //   665: aconst_null
    //   666: astore 7
    //   668: goto -52 -> 616
    //   671: astore 9
    //   673: aload 26
    //   675: astore 7
    //   677: aload 24
    //   679: astore 6
    //   681: goto -65 -> 616
    //   684: astore 8
    //   686: aconst_null
    //   687: astore 7
    //   689: aconst_null
    //   690: astore 6
    //   692: goto -188 -> 504
    //   695: astore 8
    //   697: aload 24
    //   699: astore 6
    //   701: aconst_null
    //   702: astore 7
    //   704: goto -200 -> 504
    //
    // Exception table:
    //   from	to	target	type
    //   8	17	269	finally
    //   25	47	269	finally
    //   251	255	269	finally
    //   259	263	269	finally
    //   263	266	269	finally
    //   271	274	269	finally
    //   279	284	269	finally
    //   289	294	269	finally
    //   307	311	269	finally
    //   315	319	269	finally
    //   319	322	269	finally
    //   326	331	269	finally
    //   336	341	269	finally
    //   394	398	269	finally
    //   402	406	269	finally
    //   406	409	269	finally
    //   413	418	269	finally
    //   423	428	269	finally
    //   514	519	269	finally
    //   524	529	269	finally
    //   529	532	269	finally
    //   554	559	269	finally
    //   564	569	269	finally
    //   569	572	269	finally
    //   576	581	269	finally
    //   586	591	269	finally
    //   596	601	269	finally
    //   606	611	269	finally
    //   621	626	269	finally
    //   631	636	269	finally
    //   636	639	269	finally
    //   641	646	269	finally
    //   651	656	269	finally
    //   251	255	277	java/io/IOException
    //   259	263	287	java/io/IOException
    //   307	311	324	java/io/IOException
    //   315	319	334	java/io/IOException
    //   394	398	411	java/io/IOException
    //   402	406	421	java/io/IOException
    //   462	475	494	java/lang/Exception
    //   481	491	494	java/lang/Exception
    //   534	549	494	java/lang/Exception
    //   554	559	574	java/io/IOException
    //   564	569	584	java/io/IOException
    //   514	519	594	java/io/IOException
    //   524	529	604	java/io/IOException
    //   47	189	614	finally
    //   205	247	614	finally
    //   344	362	614	finally
    //   373	390	614	finally
    //   431	437	614	finally
    //   437	444	614	finally
    //   504	509	614	finally
    //   621	626	639	java/io/IOException
    //   631	636	649	java/io/IOException
    //   444	462	659	finally
    //   462	475	671	finally
    //   481	491	671	finally
    //   534	549	671	finally
    //   47	189	684	java/lang/Exception
    //   205	247	684	java/lang/Exception
    //   344	362	684	java/lang/Exception
    //   373	390	684	java/lang/Exception
    //   431	437	684	java/lang/Exception
    //   437	444	684	java/lang/Exception
    //   444	462	695	java/lang/Exception
  }
}

/* Location:           C:\Users\THX\Desktop\aa\aa\反编译工具包\out\classes_dex2jar.jar
 * Qualified Name:     com.sohu.app.ads.sdk.f.a
 * JD-Core Version:    0.6.2
 */