package com.sohu.applist.b;

import android.content.Context;

public class b
{
  private c a;

  public b(Context paramContext)
  {
    this.a = new c(paramContext);
  }

  // ERROR //
  public java.util.ArrayList<com.sohu.applist.a.a> a()
  {
    // Byte code:
    //   0: aload_0
    //   1: monitorenter
    //   2: ldc 22
    //   4: monitorenter
    //   5: aload_0
    //   6: getfield 17	com/sohu/applist/b/b:a	Lcom/sohu/applist/b/c;
    //   9: invokevirtual 26	com/sohu/applist/b/c:getReadableDatabase	()Landroid/database/sqlite/SQLiteDatabase;
    //   12: astore_3
    //   13: new 28	java/util/ArrayList
    //   16: dup
    //   17: invokespecial 29	java/util/ArrayList:<init>	()V
    //   20: astore 4
    //   22: aload_3
    //   23: invokevirtual 34	android/database/sqlite/SQLiteDatabase:beginTransaction	()V
    //   26: aload_3
    //   27: ldc 36
    //   29: iconst_0
    //   30: anewarray 38	java/lang/String
    //   33: invokevirtual 42	android/database/sqlite/SQLiteDatabase:rawQuery	(Ljava/lang/String;[Ljava/lang/String;)Landroid/database/Cursor;
    //   36: astore 7
    //   38: aload 7
    //   40: invokeinterface 48 1 0
    //   45: ifeq +182 -> 227
    //   48: aload 4
    //   50: new 50	com/sohu/applist/a/a
    //   53: dup
    //   54: aload 7
    //   56: aload 7
    //   58: ldc 51
    //   60: invokeinterface 55 2 0
    //   65: invokeinterface 59 2 0
    //   70: invokestatic 65	com/sohu/upload/b/c:d	(Ljava/lang/String;)Ljava/lang/String;
    //   73: aload 7
    //   75: aload 7
    //   77: ldc 67
    //   79: invokeinterface 55 2 0
    //   84: invokeinterface 59 2 0
    //   89: invokestatic 65	com/sohu/upload/b/c:d	(Ljava/lang/String;)Ljava/lang/String;
    //   92: aload 7
    //   94: aload 7
    //   96: ldc 69
    //   98: invokeinterface 55 2 0
    //   103: invokeinterface 59 2 0
    //   108: invokestatic 65	com/sohu/upload/b/c:d	(Ljava/lang/String;)Ljava/lang/String;
    //   111: aload 7
    //   113: aload 7
    //   115: ldc 70
    //   117: invokeinterface 55 2 0
    //   122: invokeinterface 59 2 0
    //   127: invokestatic 65	com/sohu/upload/b/c:d	(Ljava/lang/String;)Ljava/lang/String;
    //   130: aload 7
    //   132: aload 7
    //   134: ldc 72
    //   136: invokeinterface 55 2 0
    //   141: invokeinterface 59 2 0
    //   146: invokestatic 65	com/sohu/upload/b/c:d	(Ljava/lang/String;)Ljava/lang/String;
    //   149: aload 7
    //   151: aload 7
    //   153: ldc 74
    //   155: invokeinterface 55 2 0
    //   160: invokeinterface 59 2 0
    //   165: invokestatic 65	com/sohu/upload/b/c:d	(Ljava/lang/String;)Ljava/lang/String;
    //   168: invokespecial 77	com/sohu/applist/a/a:<init>	(Ljava/lang/String;Ljava/lang/String;Ljava/lang/String;Ljava/lang/String;Ljava/lang/String;Ljava/lang/String;)V
    //   171: invokevirtual 81	java/util/ArrayList:add	(Ljava/lang/Object;)Z
    //   174: pop
    //   175: goto -137 -> 38
    //   178: astore 6
    //   180: new 83	java/lang/StringBuilder
    //   183: dup
    //   184: invokespecial 84	java/lang/StringBuilder:<init>	()V
    //   187: ldc 86
    //   189: invokevirtual 90	java/lang/StringBuilder:append	(Ljava/lang/String;)Ljava/lang/StringBuilder;
    //   192: aload 6
    //   194: invokevirtual 94	java/lang/Exception:getMessage	()Ljava/lang/String;
    //   197: invokevirtual 90	java/lang/StringBuilder:append	(Ljava/lang/String;)Ljava/lang/StringBuilder;
    //   200: ldc 96
    //   202: invokevirtual 90	java/lang/StringBuilder:append	(Ljava/lang/String;)Ljava/lang/StringBuilder;
    //   205: invokevirtual 99	java/lang/StringBuilder:toString	()Ljava/lang/String;
    //   208: invokestatic 104	com/sohu/upload/a/a:b	(Ljava/lang/String;)V
    //   211: aload_3
    //   212: invokevirtual 107	android/database/sqlite/SQLiteDatabase:endTransaction	()V
    //   215: aload_3
    //   216: invokevirtual 110	android/database/sqlite/SQLiteDatabase:close	()V
    //   219: ldc 22
    //   221: monitorexit
    //   222: aload_0
    //   223: monitorexit
    //   224: aload 4
    //   226: areturn
    //   227: new 83	java/lang/StringBuilder
    //   230: dup
    //   231: invokespecial 84	java/lang/StringBuilder:<init>	()V
    //   234: ldc 112
    //   236: invokevirtual 90	java/lang/StringBuilder:append	(Ljava/lang/String;)Ljava/lang/StringBuilder;
    //   239: aload 4
    //   241: invokevirtual 116	java/util/ArrayList:size	()I
    //   244: invokevirtual 119	java/lang/StringBuilder:append	(I)Ljava/lang/StringBuilder;
    //   247: invokevirtual 99	java/lang/StringBuilder:toString	()Ljava/lang/String;
    //   250: invokestatic 121	com/sohu/upload/a/a:a	(Ljava/lang/String;)V
    //   253: aload 7
    //   255: invokeinterface 122 1 0
    //   260: aload_3
    //   261: invokevirtual 125	android/database/sqlite/SQLiteDatabase:setTransactionSuccessful	()V
    //   264: aload_3
    //   265: invokevirtual 107	android/database/sqlite/SQLiteDatabase:endTransaction	()V
    //   268: goto -53 -> 215
    //   271: astore_2
    //   272: ldc 22
    //   274: monitorexit
    //   275: aload_2
    //   276: athrow
    //   277: astore_1
    //   278: aload_0
    //   279: monitorexit
    //   280: aload_1
    //   281: athrow
    //   282: astore 5
    //   284: aload_3
    //   285: invokevirtual 107	android/database/sqlite/SQLiteDatabase:endTransaction	()V
    //   288: aload 5
    //   290: athrow
    //
    // Exception table:
    //   from	to	target	type
    //   26	38	178	java/lang/Exception
    //   38	175	178	java/lang/Exception
    //   227	264	178	java/lang/Exception
    //   5	26	271	finally
    //   211	215	271	finally
    //   215	222	271	finally
    //   264	268	271	finally
    //   272	275	271	finally
    //   284	291	271	finally
    //   2	5	277	finally
    //   275	277	277	finally
    //   26	38	282	finally
    //   38	175	282	finally
    //   180	211	282	finally
    //   227	264	282	finally
  }

  // ERROR //
  public void a(int paramInt)
  {
    // Byte code:
    //   0: aload_0
    //   1: monitorenter
    //   2: ldc 22
    //   4: monitorenter
    //   5: new 83	java/lang/StringBuilder
    //   8: dup
    //   9: invokespecial 84	java/lang/StringBuilder:<init>	()V
    //   12: ldc 128
    //   14: invokevirtual 90	java/lang/StringBuilder:append	(Ljava/lang/String;)Ljava/lang/StringBuilder;
    //   17: iload_1
    //   18: invokevirtual 119	java/lang/StringBuilder:append	(I)Ljava/lang/StringBuilder;
    //   21: invokevirtual 99	java/lang/StringBuilder:toString	()Ljava/lang/String;
    //   24: invokestatic 104	com/sohu/upload/a/a:b	(Ljava/lang/String;)V
    //   27: aload_0
    //   28: getfield 17	com/sohu/applist/b/b:a	Lcom/sohu/applist/b/c;
    //   31: invokevirtual 131	com/sohu/applist/b/c:getWritableDatabase	()Landroid/database/sqlite/SQLiteDatabase;
    //   34: astore 4
    //   36: aload 4
    //   38: invokevirtual 34	android/database/sqlite/SQLiteDatabase:beginTransaction	()V
    //   41: iconst_1
    //   42: anewarray 38	java/lang/String
    //   45: astore 7
    //   47: aload 7
    //   49: iconst_0
    //   50: iload_1
    //   51: invokestatic 134	java/lang/String:valueOf	(I)Ljava/lang/String;
    //   54: aastore
    //   55: aload 4
    //   57: ldc 136
    //   59: aload 7
    //   61: invokevirtual 140	android/database/sqlite/SQLiteDatabase:execSQL	(Ljava/lang/String;[Ljava/lang/Object;)V
    //   64: aload 4
    //   66: invokevirtual 125	android/database/sqlite/SQLiteDatabase:setTransactionSuccessful	()V
    //   69: aload 4
    //   71: invokevirtual 107	android/database/sqlite/SQLiteDatabase:endTransaction	()V
    //   74: aload 4
    //   76: invokevirtual 110	android/database/sqlite/SQLiteDatabase:close	()V
    //   79: ldc 22
    //   81: monitorexit
    //   82: aload_0
    //   83: monitorexit
    //   84: return
    //   85: astore 6
    //   87: new 83	java/lang/StringBuilder
    //   90: dup
    //   91: invokespecial 84	java/lang/StringBuilder:<init>	()V
    //   94: ldc 86
    //   96: invokevirtual 90	java/lang/StringBuilder:append	(Ljava/lang/String;)Ljava/lang/StringBuilder;
    //   99: aload 6
    //   101: invokevirtual 94	java/lang/Exception:getMessage	()Ljava/lang/String;
    //   104: invokevirtual 90	java/lang/StringBuilder:append	(Ljava/lang/String;)Ljava/lang/StringBuilder;
    //   107: ldc 142
    //   109: invokevirtual 90	java/lang/StringBuilder:append	(Ljava/lang/String;)Ljava/lang/StringBuilder;
    //   112: invokevirtual 99	java/lang/StringBuilder:toString	()Ljava/lang/String;
    //   115: invokestatic 104	com/sohu/upload/a/a:b	(Ljava/lang/String;)V
    //   118: aload 4
    //   120: invokevirtual 107	android/database/sqlite/SQLiteDatabase:endTransaction	()V
    //   123: goto -49 -> 74
    //   126: astore_3
    //   127: ldc 22
    //   129: monitorexit
    //   130: aload_3
    //   131: athrow
    //   132: astore_2
    //   133: aload_0
    //   134: monitorexit
    //   135: aload_2
    //   136: athrow
    //   137: astore 5
    //   139: aload 4
    //   141: invokevirtual 107	android/database/sqlite/SQLiteDatabase:endTransaction	()V
    //   144: aload 5
    //   146: athrow
    //
    // Exception table:
    //   from	to	target	type
    //   41	69	85	java/lang/Exception
    //   5	41	126	finally
    //   69	74	126	finally
    //   74	82	126	finally
    //   118	123	126	finally
    //   127	130	126	finally
    //   139	147	126	finally
    //   2	5	132	finally
    //   130	132	132	finally
    //   41	69	137	finally
    //   87	118	137	finally
  }

  // ERROR //
  public void a(com.sohu.applist.a.a parama)
  {
    // Byte code:
    //   0: aload_0
    //   1: monitorenter
    //   2: ldc 22
    //   4: monitorenter
    //   5: aload_0
    //   6: getfield 17	com/sohu/applist/b/b:a	Lcom/sohu/applist/b/c;
    //   9: invokevirtual 131	com/sohu/applist/b/c:getWritableDatabase	()Landroid/database/sqlite/SQLiteDatabase;
    //   12: astore 4
    //   14: aload 4
    //   16: invokevirtual 34	android/database/sqlite/SQLiteDatabase:beginTransaction	()V
    //   19: bipush 6
    //   21: anewarray 4	java/lang/Object
    //   24: astore 7
    //   26: aload 7
    //   28: iconst_0
    //   29: aload_1
    //   30: invokevirtual 145	com/sohu/applist/a/a:b	()Ljava/lang/String;
    //   33: invokestatic 147	com/sohu/upload/b/c:c	(Ljava/lang/String;)Ljava/lang/String;
    //   36: aastore
    //   37: aload 7
    //   39: iconst_1
    //   40: aload_1
    //   41: invokevirtual 149	com/sohu/applist/a/a:c	()Ljava/lang/String;
    //   44: invokestatic 147	com/sohu/upload/b/c:c	(Ljava/lang/String;)Ljava/lang/String;
    //   47: aastore
    //   48: aload 7
    //   50: iconst_2
    //   51: aload_1
    //   52: invokevirtual 151	com/sohu/applist/a/a:d	()Ljava/lang/String;
    //   55: invokestatic 147	com/sohu/upload/b/c:c	(Ljava/lang/String;)Ljava/lang/String;
    //   58: aastore
    //   59: aload 7
    //   61: iconst_3
    //   62: aload_1
    //   63: invokevirtual 153	com/sohu/applist/a/a:e	()Ljava/lang/String;
    //   66: invokestatic 147	com/sohu/upload/b/c:c	(Ljava/lang/String;)Ljava/lang/String;
    //   69: aastore
    //   70: aload 7
    //   72: iconst_4
    //   73: aload_1
    //   74: invokevirtual 155	com/sohu/applist/a/a:f	()Ljava/lang/String;
    //   77: invokestatic 147	com/sohu/upload/b/c:c	(Ljava/lang/String;)Ljava/lang/String;
    //   80: aastore
    //   81: aload 7
    //   83: iconst_5
    //   84: aload_1
    //   85: invokevirtual 158	com/sohu/applist/a/a:g	()Ljava/lang/String;
    //   88: invokestatic 147	com/sohu/upload/b/c:c	(Ljava/lang/String;)Ljava/lang/String;
    //   91: aastore
    //   92: aload 4
    //   94: ldc 160
    //   96: aload 7
    //   98: invokevirtual 140	android/database/sqlite/SQLiteDatabase:execSQL	(Ljava/lang/String;[Ljava/lang/Object;)V
    //   101: aload 4
    //   103: invokevirtual 125	android/database/sqlite/SQLiteDatabase:setTransactionSuccessful	()V
    //   106: aload 4
    //   108: invokevirtual 107	android/database/sqlite/SQLiteDatabase:endTransaction	()V
    //   111: aload 4
    //   113: invokevirtual 110	android/database/sqlite/SQLiteDatabase:close	()V
    //   116: ldc 22
    //   118: monitorexit
    //   119: aload_0
    //   120: monitorexit
    //   121: return
    //   122: astore 6
    //   124: new 83	java/lang/StringBuilder
    //   127: dup
    //   128: invokespecial 84	java/lang/StringBuilder:<init>	()V
    //   131: ldc 86
    //   133: invokevirtual 90	java/lang/StringBuilder:append	(Ljava/lang/String;)Ljava/lang/StringBuilder;
    //   136: aload 6
    //   138: invokevirtual 94	java/lang/Exception:getMessage	()Ljava/lang/String;
    //   141: invokevirtual 90	java/lang/StringBuilder:append	(Ljava/lang/String;)Ljava/lang/StringBuilder;
    //   144: ldc 162
    //   146: invokevirtual 90	java/lang/StringBuilder:append	(Ljava/lang/String;)Ljava/lang/StringBuilder;
    //   149: invokevirtual 99	java/lang/StringBuilder:toString	()Ljava/lang/String;
    //   152: invokestatic 104	com/sohu/upload/a/a:b	(Ljava/lang/String;)V
    //   155: aload 4
    //   157: invokevirtual 107	android/database/sqlite/SQLiteDatabase:endTransaction	()V
    //   160: goto -49 -> 111
    //   163: astore_3
    //   164: ldc 22
    //   166: monitorexit
    //   167: aload_3
    //   168: athrow
    //   169: astore_2
    //   170: aload_0
    //   171: monitorexit
    //   172: aload_2
    //   173: athrow
    //   174: astore 5
    //   176: aload 4
    //   178: invokevirtual 107	android/database/sqlite/SQLiteDatabase:endTransaction	()V
    //   181: aload 5
    //   183: athrow
    //
    // Exception table:
    //   from	to	target	type
    //   19	106	122	java/lang/Exception
    //   5	19	163	finally
    //   106	111	163	finally
    //   111	119	163	finally
    //   155	160	163	finally
    //   164	167	163	finally
    //   176	184	163	finally
    //   2	5	169	finally
    //   167	169	169	finally
    //   19	106	174	finally
    //   124	155	174	finally
  }

  // ERROR //
  public com.sohu.applist.a.a b()
  {
    // Byte code:
    //   0: aload_0
    //   1: monitorenter
    //   2: ldc 22
    //   4: monitorenter
    //   5: aload_0
    //   6: getfield 17	com/sohu/applist/b/b:a	Lcom/sohu/applist/b/c;
    //   9: invokevirtual 26	com/sohu/applist/b/c:getReadableDatabase	()Landroid/database/sqlite/SQLiteDatabase;
    //   12: astore_3
    //   13: new 50	com/sohu/applist/a/a
    //   16: dup
    //   17: invokespecial 164	com/sohu/applist/a/a:<init>	()V
    //   20: astore 4
    //   22: aload_3
    //   23: invokevirtual 34	android/database/sqlite/SQLiteDatabase:beginTransaction	()V
    //   26: aload_3
    //   27: ldc 166
    //   29: iconst_0
    //   30: anewarray 38	java/lang/String
    //   33: invokevirtual 42	android/database/sqlite/SQLiteDatabase:rawQuery	(Ljava/lang/String;[Ljava/lang/String;)Landroid/database/Cursor;
    //   36: astore 7
    //   38: aload 7
    //   40: invokeinterface 48 1 0
    //   45: ifeq +227 -> 272
    //   48: aload 4
    //   50: aload 7
    //   52: aload 7
    //   54: ldc 168
    //   56: invokeinterface 55 2 0
    //   61: invokeinterface 172 2 0
    //   66: invokevirtual 174	com/sohu/applist/a/a:a	(I)V
    //   69: aload 4
    //   71: aload 7
    //   73: aload 7
    //   75: ldc 51
    //   77: invokeinterface 55 2 0
    //   82: invokeinterface 59 2 0
    //   87: invokestatic 65	com/sohu/upload/b/c:d	(Ljava/lang/String;)Ljava/lang/String;
    //   90: invokevirtual 175	com/sohu/applist/a/a:a	(Ljava/lang/String;)V
    //   93: aload 4
    //   95: aload 7
    //   97: aload 7
    //   99: ldc 67
    //   101: invokeinterface 55 2 0
    //   106: invokeinterface 59 2 0
    //   111: invokestatic 65	com/sohu/upload/b/c:d	(Ljava/lang/String;)Ljava/lang/String;
    //   114: invokevirtual 176	com/sohu/applist/a/a:b	(Ljava/lang/String;)V
    //   117: aload 4
    //   119: aload 7
    //   121: aload 7
    //   123: ldc 69
    //   125: invokeinterface 55 2 0
    //   130: invokeinterface 59 2 0
    //   135: invokestatic 65	com/sohu/upload/b/c:d	(Ljava/lang/String;)Ljava/lang/String;
    //   138: invokevirtual 178	com/sohu/applist/a/a:c	(Ljava/lang/String;)V
    //   141: aload 4
    //   143: aload 7
    //   145: aload 7
    //   147: ldc 70
    //   149: invokeinterface 55 2 0
    //   154: invokeinterface 59 2 0
    //   159: invokestatic 65	com/sohu/upload/b/c:d	(Ljava/lang/String;)Ljava/lang/String;
    //   162: invokevirtual 180	com/sohu/applist/a/a:d	(Ljava/lang/String;)V
    //   165: aload 4
    //   167: aload 7
    //   169: aload 7
    //   171: ldc 72
    //   173: invokeinterface 55 2 0
    //   178: invokeinterface 59 2 0
    //   183: invokestatic 65	com/sohu/upload/b/c:d	(Ljava/lang/String;)Ljava/lang/String;
    //   186: invokevirtual 182	com/sohu/applist/a/a:e	(Ljava/lang/String;)V
    //   189: aload 4
    //   191: aload 7
    //   193: aload 7
    //   195: ldc 74
    //   197: invokeinterface 55 2 0
    //   202: invokeinterface 59 2 0
    //   207: invokestatic 65	com/sohu/upload/b/c:d	(Ljava/lang/String;)Ljava/lang/String;
    //   210: invokevirtual 184	com/sohu/applist/a/a:f	(Ljava/lang/String;)V
    //   213: aload 7
    //   215: invokeinterface 122 1 0
    //   220: goto -182 -> 38
    //   223: astore 6
    //   225: new 83	java/lang/StringBuilder
    //   228: dup
    //   229: invokespecial 84	java/lang/StringBuilder:<init>	()V
    //   232: ldc 86
    //   234: invokevirtual 90	java/lang/StringBuilder:append	(Ljava/lang/String;)Ljava/lang/StringBuilder;
    //   237: aload 6
    //   239: invokevirtual 94	java/lang/Exception:getMessage	()Ljava/lang/String;
    //   242: invokevirtual 90	java/lang/StringBuilder:append	(Ljava/lang/String;)Ljava/lang/StringBuilder;
    //   245: ldc 96
    //   247: invokevirtual 90	java/lang/StringBuilder:append	(Ljava/lang/String;)Ljava/lang/StringBuilder;
    //   250: invokevirtual 99	java/lang/StringBuilder:toString	()Ljava/lang/String;
    //   253: invokestatic 104	com/sohu/upload/a/a:b	(Ljava/lang/String;)V
    //   256: aload_3
    //   257: invokevirtual 107	android/database/sqlite/SQLiteDatabase:endTransaction	()V
    //   260: aload_3
    //   261: invokevirtual 110	android/database/sqlite/SQLiteDatabase:close	()V
    //   264: ldc 22
    //   266: monitorexit
    //   267: aload_0
    //   268: monitorexit
    //   269: aload 4
    //   271: areturn
    //   272: aload_3
    //   273: invokevirtual 125	android/database/sqlite/SQLiteDatabase:setTransactionSuccessful	()V
    //   276: aload_3
    //   277: invokevirtual 107	android/database/sqlite/SQLiteDatabase:endTransaction	()V
    //   280: goto -20 -> 260
    //   283: astore_2
    //   284: ldc 22
    //   286: monitorexit
    //   287: aload_2
    //   288: athrow
    //   289: astore_1
    //   290: aload_0
    //   291: monitorexit
    //   292: aload_1
    //   293: athrow
    //   294: astore 5
    //   296: aload_3
    //   297: invokevirtual 107	android/database/sqlite/SQLiteDatabase:endTransaction	()V
    //   300: aload 5
    //   302: athrow
    //
    // Exception table:
    //   from	to	target	type
    //   26	38	223	java/lang/Exception
    //   38	220	223	java/lang/Exception
    //   272	276	223	java/lang/Exception
    //   5	26	283	finally
    //   256	260	283	finally
    //   260	267	283	finally
    //   276	280	283	finally
    //   284	287	283	finally
    //   296	303	283	finally
    //   2	5	289	finally
    //   287	289	289	finally
    //   26	38	294	finally
    //   38	220	294	finally
    //   225	256	294	finally
    //   272	276	294	finally
  }

  // ERROR //
  public void c()
  {
    // Byte code:
    //   0: aload_0
    //   1: monitorenter
    //   2: ldc 22
    //   4: monitorenter
    //   5: aload_0
    //   6: getfield 17	com/sohu/applist/b/b:a	Lcom/sohu/applist/b/c;
    //   9: invokevirtual 131	com/sohu/applist/b/c:getWritableDatabase	()Landroid/database/sqlite/SQLiteDatabase;
    //   12: astore_3
    //   13: aload_3
    //   14: invokevirtual 34	android/database/sqlite/SQLiteDatabase:beginTransaction	()V
    //   17: aload_3
    //   18: ldc 186
    //   20: iconst_0
    //   21: anewarray 4	java/lang/Object
    //   24: invokevirtual 140	android/database/sqlite/SQLiteDatabase:execSQL	(Ljava/lang/String;[Ljava/lang/Object;)V
    //   27: aload_3
    //   28: invokevirtual 125	android/database/sqlite/SQLiteDatabase:setTransactionSuccessful	()V
    //   31: aload_3
    //   32: invokevirtual 107	android/database/sqlite/SQLiteDatabase:endTransaction	()V
    //   35: aload_3
    //   36: invokevirtual 110	android/database/sqlite/SQLiteDatabase:close	()V
    //   39: ldc 22
    //   41: monitorexit
    //   42: aload_0
    //   43: monitorexit
    //   44: return
    //   45: astore 5
    //   47: new 83	java/lang/StringBuilder
    //   50: dup
    //   51: invokespecial 84	java/lang/StringBuilder:<init>	()V
    //   54: ldc 86
    //   56: invokevirtual 90	java/lang/StringBuilder:append	(Ljava/lang/String;)Ljava/lang/StringBuilder;
    //   59: aload 5
    //   61: invokevirtual 94	java/lang/Exception:getMessage	()Ljava/lang/String;
    //   64: invokevirtual 90	java/lang/StringBuilder:append	(Ljava/lang/String;)Ljava/lang/StringBuilder;
    //   67: ldc 188
    //   69: invokevirtual 90	java/lang/StringBuilder:append	(Ljava/lang/String;)Ljava/lang/StringBuilder;
    //   72: invokevirtual 99	java/lang/StringBuilder:toString	()Ljava/lang/String;
    //   75: invokestatic 104	com/sohu/upload/a/a:b	(Ljava/lang/String;)V
    //   78: aload_3
    //   79: invokevirtual 107	android/database/sqlite/SQLiteDatabase:endTransaction	()V
    //   82: goto -47 -> 35
    //   85: astore_2
    //   86: ldc 22
    //   88: monitorexit
    //   89: aload_2
    //   90: athrow
    //   91: astore_1
    //   92: aload_0
    //   93: monitorexit
    //   94: aload_1
    //   95: athrow
    //   96: astore 4
    //   98: aload_3
    //   99: invokevirtual 107	android/database/sqlite/SQLiteDatabase:endTransaction	()V
    //   102: aload 4
    //   104: athrow
    //
    // Exception table:
    //   from	to	target	type
    //   17	31	45	java/lang/Exception
    //   5	17	85	finally
    //   31	35	85	finally
    //   35	42	85	finally
    //   78	82	85	finally
    //   86	89	85	finally
    //   98	105	85	finally
    //   2	5	91	finally
    //   89	91	91	finally
    //   17	31	96	finally
    //   47	78	96	finally
  }
}

/* Location:           C:\Users\THX\Desktop\aa\aa\反编译工具包\out\classes_dex2jar.jar
 * Qualified Name:     com.sohu.applist.b.b
 * JD-Core Version:    0.6.2
 */