package com.sohu.app.ads.sdk.a;

import android.content.Context;

public class c
{
  private static a a;

  public c(Context paramContext)
  {
    a = new a(paramContext);
  }

  // ERROR //
  public int a(java.lang.String paramString1, java.lang.String paramString2)
  {
    // Byte code:
    //   0: iconst_0
    //   1: istore_3
    //   2: aload_0
    //   3: monitorenter
    //   4: ldc 2
    //   6: monitorenter
    //   7: getstatic 17	com/sohu/app/ads/sdk/a/c:a	Lcom/sohu/app/ads/sdk/a/a;
    //   10: invokevirtual 24	com/sohu/app/ads/sdk/a/a:getReadableDatabase	()Landroid/database/sqlite/SQLiteDatabase;
    //   13: astore 6
    //   15: aload 6
    //   17: invokevirtual 29	android/database/sqlite/SQLiteDatabase:beginTransaction	()V
    //   20: aload 6
    //   22: ldc 31
    //   24: iconst_2
    //   25: anewarray 33	java/lang/String
    //   28: dup
    //   29: iconst_0
    //   30: aload_1
    //   31: aastore
    //   32: dup
    //   33: iconst_1
    //   34: aload_2
    //   35: aastore
    //   36: invokevirtual 37	android/database/sqlite/SQLiteDatabase:rawQuery	(Ljava/lang/String;[Ljava/lang/String;)Landroid/database/Cursor;
    //   39: astore 9
    //   41: aload 9
    //   43: invokeinterface 43 1 0
    //   48: istore 10
    //   50: iconst_0
    //   51: istore_3
    //   52: iload 10
    //   54: ifeq +12 -> 66
    //   57: aload 9
    //   59: iconst_0
    //   60: invokeinterface 47 2 0
    //   65: istore_3
    //   66: aload 9
    //   68: invokeinterface 50 1 0
    //   73: aload 6
    //   75: invokevirtual 53	android/database/sqlite/SQLiteDatabase:setTransactionSuccessful	()V
    //   78: aload 6
    //   80: invokevirtual 56	android/database/sqlite/SQLiteDatabase:endTransaction	()V
    //   83: aload 6
    //   85: invokevirtual 57	android/database/sqlite/SQLiteDatabase:close	()V
    //   88: ldc 2
    //   90: monitorexit
    //   91: aload_0
    //   92: monitorexit
    //   93: iload_3
    //   94: ireturn
    //   95: astore 8
    //   97: aload 8
    //   99: invokevirtual 61	java/lang/Exception:toString	()Ljava/lang/String;
    //   102: invokestatic 67	com/sohu/app/ads/sdk/c/a:c	(Ljava/lang/String;)V
    //   105: aload 6
    //   107: invokevirtual 56	android/database/sqlite/SQLiteDatabase:endTransaction	()V
    //   110: goto -27 -> 83
    //   113: astore 5
    //   115: ldc 2
    //   117: monitorexit
    //   118: aload 5
    //   120: athrow
    //   121: astore 4
    //   123: aload_0
    //   124: monitorexit
    //   125: aload 4
    //   127: athrow
    //   128: astore 7
    //   130: aload 6
    //   132: invokevirtual 56	android/database/sqlite/SQLiteDatabase:endTransaction	()V
    //   135: aload 7
    //   137: athrow
    //
    // Exception table:
    //   from	to	target	type
    //   20	50	95	java/lang/Exception
    //   57	66	95	java/lang/Exception
    //   66	78	95	java/lang/Exception
    //   7	20	113	finally
    //   78	83	113	finally
    //   83	91	113	finally
    //   105	110	113	finally
    //   115	118	113	finally
    //   130	138	113	finally
    //   4	7	121	finally
    //   118	121	121	finally
    //   20	50	128	finally
    //   57	66	128	finally
    //   66	78	128	finally
    //   97	105	128	finally
  }

  // ERROR //
  public void a(java.lang.String paramString)
  {
    // Byte code:
    //   0: aload_0
    //   1: monitorenter
    //   2: ldc 2
    //   4: monitorenter
    //   5: getstatic 17	com/sohu/app/ads/sdk/a/c:a	Lcom/sohu/app/ads/sdk/a/a;
    //   8: invokevirtual 70	com/sohu/app/ads/sdk/a/a:getWritableDatabase	()Landroid/database/sqlite/SQLiteDatabase;
    //   11: astore 4
    //   13: aload 4
    //   15: invokevirtual 29	android/database/sqlite/SQLiteDatabase:beginTransaction	()V
    //   18: aload 4
    //   20: ldc 72
    //   22: iconst_1
    //   23: anewarray 33	java/lang/String
    //   26: dup
    //   27: iconst_0
    //   28: aload_1
    //   29: aastore
    //   30: invokevirtual 76	android/database/sqlite/SQLiteDatabase:execSQL	(Ljava/lang/String;[Ljava/lang/Object;)V
    //   33: aload 4
    //   35: invokevirtual 53	android/database/sqlite/SQLiteDatabase:setTransactionSuccessful	()V
    //   38: aload 4
    //   40: invokevirtual 56	android/database/sqlite/SQLiteDatabase:endTransaction	()V
    //   43: aload 4
    //   45: invokevirtual 57	android/database/sqlite/SQLiteDatabase:close	()V
    //   48: ldc 2
    //   50: monitorexit
    //   51: aload_0
    //   52: monitorexit
    //   53: return
    //   54: astore 6
    //   56: aload 6
    //   58: invokevirtual 61	java/lang/Exception:toString	()Ljava/lang/String;
    //   61: invokestatic 67	com/sohu/app/ads/sdk/c/a:c	(Ljava/lang/String;)V
    //   64: aload 4
    //   66: invokevirtual 56	android/database/sqlite/SQLiteDatabase:endTransaction	()V
    //   69: goto -26 -> 43
    //   72: astore_3
    //   73: ldc 2
    //   75: monitorexit
    //   76: aload_3
    //   77: athrow
    //   78: astore_2
    //   79: aload_0
    //   80: monitorexit
    //   81: aload_2
    //   82: athrow
    //   83: astore 5
    //   85: aload 4
    //   87: invokevirtual 56	android/database/sqlite/SQLiteDatabase:endTransaction	()V
    //   90: aload 5
    //   92: athrow
    //
    // Exception table:
    //   from	to	target	type
    //   18	38	54	java/lang/Exception
    //   5	18	72	finally
    //   38	43	72	finally
    //   43	51	72	finally
    //   64	69	72	finally
    //   73	76	72	finally
    //   85	93	72	finally
    //   2	5	78	finally
    //   76	78	78	finally
    //   18	38	83	finally
    //   56	64	83	finally
  }

  // ERROR //
  public void a(java.lang.String paramString, com.sohu.app.ads.sdk.model.AdsResponse paramAdsResponse)
  {
    // Byte code:
    //   0: aload_0
    //   1: monitorenter
    //   2: ldc 2
    //   4: monitorenter
    //   5: getstatic 17	com/sohu/app/ads/sdk/a/c:a	Lcom/sohu/app/ads/sdk/a/a;
    //   8: invokevirtual 70	com/sohu/app/ads/sdk/a/a:getWritableDatabase	()Landroid/database/sqlite/SQLiteDatabase;
    //   11: astore 5
    //   13: aload 5
    //   15: invokevirtual 29	android/database/sqlite/SQLiteDatabase:beginTransaction	()V
    //   18: aload_2
    //   19: ifnull +319 -> 338
    //   22: aload_2
    //   23: invokevirtual 83	com/sohu/app/ads/sdk/model/AdsResponse:getImpression	()Ljava/util/ArrayList;
    //   26: astore 8
    //   28: aconst_null
    //   29: astore 9
    //   31: aload 8
    //   33: ifnull +133 -> 166
    //   36: aload 8
    //   38: invokevirtual 89	java/util/ArrayList:size	()I
    //   41: istore 10
    //   43: aconst_null
    //   44: astore 9
    //   46: iload 10
    //   48: ifle +118 -> 166
    //   51: new 91	java/lang/StringBuilder
    //   54: dup
    //   55: invokespecial 92	java/lang/StringBuilder:<init>	()V
    //   58: astore 11
    //   60: aload 8
    //   62: invokevirtual 96	java/util/ArrayList:iterator	()Ljava/util/Iterator;
    //   65: astore 12
    //   67: aload 12
    //   69: invokeinterface 101 1 0
    //   74: ifeq +70 -> 144
    //   77: aload 12
    //   79: invokeinterface 105 1 0
    //   84: checkcast 33	java/lang/String
    //   87: astore 15
    //   89: aload 11
    //   91: new 91	java/lang/StringBuilder
    //   94: dup
    //   95: invokespecial 92	java/lang/StringBuilder:<init>	()V
    //   98: aload 15
    //   100: invokevirtual 109	java/lang/StringBuilder:append	(Ljava/lang/String;)Ljava/lang/StringBuilder;
    //   103: ldc 111
    //   105: invokevirtual 109	java/lang/StringBuilder:append	(Ljava/lang/String;)Ljava/lang/StringBuilder;
    //   108: invokevirtual 112	java/lang/StringBuilder:toString	()Ljava/lang/String;
    //   111: invokevirtual 109	java/lang/StringBuilder:append	(Ljava/lang/String;)Ljava/lang/StringBuilder;
    //   114: pop
    //   115: goto -48 -> 67
    //   118: astore 7
    //   120: aload 7
    //   122: invokevirtual 61	java/lang/Exception:toString	()Ljava/lang/String;
    //   125: invokestatic 67	com/sohu/app/ads/sdk/c/a:c	(Ljava/lang/String;)V
    //   128: aload 5
    //   130: invokevirtual 56	android/database/sqlite/SQLiteDatabase:endTransaction	()V
    //   133: aload 5
    //   135: invokevirtual 57	android/database/sqlite/SQLiteDatabase:close	()V
    //   138: ldc 2
    //   140: monitorexit
    //   141: aload_0
    //   142: monitorexit
    //   143: return
    //   144: aload 11
    //   146: invokevirtual 112	java/lang/StringBuilder:toString	()Ljava/lang/String;
    //   149: astore 13
    //   151: aload 13
    //   153: iconst_0
    //   154: iconst_m1
    //   155: aload 13
    //   157: invokevirtual 115	java/lang/String:length	()I
    //   160: iadd
    //   161: invokevirtual 119	java/lang/String:substring	(II)Ljava/lang/String;
    //   164: astore 9
    //   166: bipush 17
    //   168: anewarray 4	java/lang/Object
    //   171: astore 14
    //   173: aload 14
    //   175: iconst_0
    //   176: aload_1
    //   177: aastore
    //   178: aload 14
    //   180: iconst_1
    //   181: aload_2
    //   182: invokevirtual 122	com/sohu/app/ads/sdk/model/AdsResponse:getAdSequence	()I
    //   185: invokestatic 128	java/lang/Integer:valueOf	(I)Ljava/lang/Integer;
    //   188: aastore
    //   189: aload 14
    //   191: iconst_2
    //   192: iconst_1
    //   193: invokestatic 128	java/lang/Integer:valueOf	(I)Ljava/lang/Integer;
    //   196: aastore
    //   197: aload 14
    //   199: iconst_3
    //   200: aload 9
    //   202: aastore
    //   203: aload 14
    //   205: iconst_4
    //   206: aload_2
    //   207: invokevirtual 131	com/sohu/app/ads/sdk/model/AdsResponse:getDuration	()I
    //   210: invokestatic 128	java/lang/Integer:valueOf	(I)Ljava/lang/Integer;
    //   213: aastore
    //   214: aload 14
    //   216: iconst_5
    //   217: aload_2
    //   218: invokevirtual 134	com/sohu/app/ads/sdk/model/AdsResponse:getClickThrough	()Ljava/lang/String;
    //   221: aastore
    //   222: aload 14
    //   224: bipush 6
    //   226: aload_2
    //   227: invokevirtual 137	com/sohu/app/ads/sdk/model/AdsResponse:getClickTracking	()Ljava/lang/String;
    //   230: aastore
    //   231: aload 14
    //   233: bipush 7
    //   235: aload_2
    //   236: invokevirtual 140	com/sohu/app/ads/sdk/model/AdsResponse:getMediaFile	()Ljava/lang/String;
    //   239: aastore
    //   240: aload 14
    //   242: bipush 8
    //   244: aload_2
    //   245: invokevirtual 143	com/sohu/app/ads/sdk/model/AdsResponse:getCreativeView	()Ljava/lang/String;
    //   248: aastore
    //   249: aload 14
    //   251: bipush 9
    //   253: aload_2
    //   254: invokevirtual 146	com/sohu/app/ads/sdk/model/AdsResponse:getStart	()Ljava/lang/String;
    //   257: aastore
    //   258: aload 14
    //   260: bipush 10
    //   262: aload_2
    //   263: invokevirtual 149	com/sohu/app/ads/sdk/model/AdsResponse:getFirstQuartile	()Ljava/lang/String;
    //   266: aastore
    //   267: aload 14
    //   269: bipush 11
    //   271: aload_2
    //   272: invokevirtual 152	com/sohu/app/ads/sdk/model/AdsResponse:getMidpoint	()Ljava/lang/String;
    //   275: aastore
    //   276: aload 14
    //   278: bipush 12
    //   280: aload_2
    //   281: invokevirtual 155	com/sohu/app/ads/sdk/model/AdsResponse:getThirdQuartile	()Ljava/lang/String;
    //   284: aastore
    //   285: aload 14
    //   287: bipush 13
    //   289: aload_2
    //   290: invokevirtual 158	com/sohu/app/ads/sdk/model/AdsResponse:getComplete	()Ljava/lang/String;
    //   293: aastore
    //   294: aload 14
    //   296: bipush 14
    //   298: aload_2
    //   299: invokevirtual 161	com/sohu/app/ads/sdk/model/AdsResponse:getSdkTracking	()Ljava/util/ArrayList;
    //   302: invokevirtual 162	java/util/ArrayList:toString	()Ljava/lang/String;
    //   305: aastore
    //   306: aload 14
    //   308: bipush 15
    //   310: aload_2
    //   311: invokevirtual 165	com/sohu/app/ads/sdk/model/AdsResponse:getSdkClickTracking	()Ljava/util/ArrayList;
    //   314: invokevirtual 162	java/util/ArrayList:toString	()Ljava/lang/String;
    //   317: aastore
    //   318: aload 14
    //   320: bipush 16
    //   322: invokestatic 171	java/lang/System:currentTimeMillis	()J
    //   325: invokestatic 176	java/lang/Long:valueOf	(J)Ljava/lang/Long;
    //   328: aastore
    //   329: aload 5
    //   331: ldc 178
    //   333: aload 14
    //   335: invokevirtual 76	android/database/sqlite/SQLiteDatabase:execSQL	(Ljava/lang/String;[Ljava/lang/Object;)V
    //   338: aload 5
    //   340: invokevirtual 53	android/database/sqlite/SQLiteDatabase:setTransactionSuccessful	()V
    //   343: aload 5
    //   345: invokevirtual 56	android/database/sqlite/SQLiteDatabase:endTransaction	()V
    //   348: goto -215 -> 133
    //   351: astore 4
    //   353: ldc 2
    //   355: monitorexit
    //   356: aload 4
    //   358: athrow
    //   359: astore_3
    //   360: aload_0
    //   361: monitorexit
    //   362: aload_3
    //   363: athrow
    //   364: astore 6
    //   366: aload 5
    //   368: invokevirtual 56	android/database/sqlite/SQLiteDatabase:endTransaction	()V
    //   371: aload 6
    //   373: athrow
    //
    // Exception table:
    //   from	to	target	type
    //   22	28	118	java/lang/Exception
    //   36	43	118	java/lang/Exception
    //   51	67	118	java/lang/Exception
    //   67	115	118	java/lang/Exception
    //   144	166	118	java/lang/Exception
    //   166	338	118	java/lang/Exception
    //   338	343	118	java/lang/Exception
    //   5	18	351	finally
    //   128	133	351	finally
    //   133	141	351	finally
    //   343	348	351	finally
    //   353	356	351	finally
    //   366	374	351	finally
    //   2	5	359	finally
    //   356	359	359	finally
    //   22	28	364	finally
    //   36	43	364	finally
    //   51	67	364	finally
    //   67	115	364	finally
    //   120	128	364	finally
    //   144	166	364	finally
    //   166	338	364	finally
    //   338	343	364	finally
  }

  // ERROR //
  public java.util.ArrayList<com.sohu.app.ads.sdk.model.AdsResponse> b(java.lang.String paramString)
  {
    // Byte code:
    //   0: aload_0
    //   1: monitorenter
    //   2: ldc 2
    //   4: monitorenter
    //   5: getstatic 17	com/sohu/app/ads/sdk/a/c:a	Lcom/sohu/app/ads/sdk/a/a;
    //   8: invokevirtual 24	com/sohu/app/ads/sdk/a/a:getReadableDatabase	()Landroid/database/sqlite/SQLiteDatabase;
    //   11: astore 4
    //   13: new 85	java/util/ArrayList
    //   16: dup
    //   17: invokespecial 181	java/util/ArrayList:<init>	()V
    //   20: astore 5
    //   22: aload 4
    //   24: invokevirtual 29	android/database/sqlite/SQLiteDatabase:beginTransaction	()V
    //   27: aload 4
    //   29: ldc 183
    //   31: iconst_1
    //   32: anewarray 33	java/lang/String
    //   35: dup
    //   36: iconst_0
    //   37: aload_1
    //   38: aastore
    //   39: invokevirtual 37	android/database/sqlite/SQLiteDatabase:rawQuery	(Ljava/lang/String;[Ljava/lang/String;)Landroid/database/Cursor;
    //   42: astore 8
    //   44: aload 8
    //   46: invokeinterface 43 1 0
    //   51: ifeq +763 -> 814
    //   54: new 79	com/sohu/app/ads/sdk/model/AdsResponse
    //   57: dup
    //   58: invokespecial 184	com/sohu/app/ads/sdk/model/AdsResponse:<init>	()V
    //   61: astore 9
    //   63: new 85	java/util/ArrayList
    //   66: dup
    //   67: invokespecial 181	java/util/ArrayList:<init>	()V
    //   70: astore 10
    //   72: aload 9
    //   74: aload 8
    //   76: aload 8
    //   78: ldc 186
    //   80: invokeinterface 190 2 0
    //   85: invokeinterface 47 2 0
    //   90: invokevirtual 194	com/sohu/app/ads/sdk/model/AdsResponse:setAdSequence	(I)V
    //   93: aload 9
    //   95: aload 8
    //   97: aload 8
    //   99: ldc 196
    //   101: invokeinterface 190 2 0
    //   106: invokeinterface 47 2 0
    //   111: invokevirtual 199	com/sohu/app/ads/sdk/model/AdsResponse:setOfflineAd	(I)V
    //   114: aload 8
    //   116: aload 8
    //   118: ldc 201
    //   120: invokeinterface 190 2 0
    //   125: invokeinterface 205 2 0
    //   130: ldc 111
    //   132: invokevirtual 209	java/lang/String:split	(Ljava/lang/String;)[Ljava/lang/String;
    //   135: astore 33
    //   137: iconst_0
    //   138: istore 34
    //   140: aload 33
    //   142: ifnull +28 -> 170
    //   145: iload 34
    //   147: aload 33
    //   149: arraylength
    //   150: if_icmpge +20 -> 170
    //   153: aload 10
    //   155: aload 33
    //   157: iload 34
    //   159: aaload
    //   160: invokevirtual 213	java/util/ArrayList:add	(Ljava/lang/Object;)Z
    //   163: pop
    //   164: iinc 34 1
    //   167: goto -27 -> 140
    //   170: aload 9
    //   172: aload 10
    //   174: invokevirtual 217	com/sohu/app/ads/sdk/model/AdsResponse:setImpression	(Ljava/util/ArrayList;)V
    //   177: aload 9
    //   179: aload 8
    //   181: aload 8
    //   183: ldc 219
    //   185: invokeinterface 190 2 0
    //   190: invokeinterface 205 2 0
    //   195: invokestatic 222	java/lang/Integer:parseInt	(Ljava/lang/String;)I
    //   198: invokevirtual 225	com/sohu/app/ads/sdk/model/AdsResponse:setDuration	(I)V
    //   201: aload 9
    //   203: aload 8
    //   205: aload 8
    //   207: ldc 227
    //   209: invokeinterface 190 2 0
    //   214: invokeinterface 205 2 0
    //   219: invokevirtual 230	com/sohu/app/ads/sdk/model/AdsResponse:setClickThrough	(Ljava/lang/String;)V
    //   222: aload 9
    //   224: aload 8
    //   226: aload 8
    //   228: ldc 232
    //   230: invokeinterface 190 2 0
    //   235: invokeinterface 205 2 0
    //   240: invokevirtual 235	com/sohu/app/ads/sdk/model/AdsResponse:setClickTracking	(Ljava/lang/String;)V
    //   243: aload 9
    //   245: aload 8
    //   247: aload 8
    //   249: ldc 237
    //   251: invokeinterface 190 2 0
    //   256: invokeinterface 205 2 0
    //   261: invokevirtual 240	com/sohu/app/ads/sdk/model/AdsResponse:setMediaFile	(Ljava/lang/String;)V
    //   264: aload 9
    //   266: aload 8
    //   268: aload 8
    //   270: ldc 242
    //   272: invokeinterface 190 2 0
    //   277: invokeinterface 205 2 0
    //   282: invokevirtual 245	com/sohu/app/ads/sdk/model/AdsResponse:setCreativeView	(Ljava/lang/String;)V
    //   285: aload 9
    //   287: aload 8
    //   289: aload 8
    //   291: ldc 247
    //   293: invokeinterface 190 2 0
    //   298: invokeinterface 205 2 0
    //   303: invokevirtual 250	com/sohu/app/ads/sdk/model/AdsResponse:setStart	(Ljava/lang/String;)V
    //   306: aload 9
    //   308: aload 8
    //   310: aload 8
    //   312: ldc 252
    //   314: invokeinterface 190 2 0
    //   319: invokeinterface 205 2 0
    //   324: invokevirtual 255	com/sohu/app/ads/sdk/model/AdsResponse:setFirstQuartile	(Ljava/lang/String;)V
    //   327: aload 9
    //   329: aload 8
    //   331: aload 8
    //   333: ldc_w 257
    //   336: invokeinterface 190 2 0
    //   341: invokeinterface 205 2 0
    //   346: invokevirtual 260	com/sohu/app/ads/sdk/model/AdsResponse:setMidpoint	(Ljava/lang/String;)V
    //   349: aload 9
    //   351: aload 8
    //   353: aload 8
    //   355: ldc_w 262
    //   358: invokeinterface 190 2 0
    //   363: invokeinterface 205 2 0
    //   368: invokevirtual 265	com/sohu/app/ads/sdk/model/AdsResponse:setThirdQuartile	(Ljava/lang/String;)V
    //   371: aload 9
    //   373: aload 8
    //   375: aload 8
    //   377: ldc_w 267
    //   380: invokeinterface 190 2 0
    //   385: invokeinterface 205 2 0
    //   390: invokevirtual 270	com/sohu/app/ads/sdk/model/AdsResponse:setComplete	(Ljava/lang/String;)V
    //   393: aload 9
    //   395: aload 8
    //   397: aload 8
    //   399: ldc_w 272
    //   402: invokeinterface 190 2 0
    //   407: invokeinterface 205 2 0
    //   412: invokevirtual 275	com/sohu/app/ads/sdk/model/AdsResponse:setTime	(Ljava/lang/String;)V
    //   415: aload 8
    //   417: aload 8
    //   419: ldc_w 277
    //   422: invokeinterface 190 2 0
    //   427: invokeinterface 205 2 0
    //   432: astore 13
    //   434: new 279	org/json/JSONArray
    //   437: dup
    //   438: aload 13
    //   440: invokespecial 281	org/json/JSONArray:<init>	(Ljava/lang/String;)V
    //   443: astore 14
    //   445: iconst_0
    //   446: istore 15
    //   448: iload 15
    //   450: aload 14
    //   452: invokevirtual 282	org/json/JSONArray:length	()I
    //   455: if_icmpge +204 -> 659
    //   458: new 284	com/sohu/app/ads/sdk/model/d
    //   461: dup
    //   462: invokespecial 285	com/sohu/app/ads/sdk/model/d:<init>	()V
    //   465: astore 27
    //   467: aload 14
    //   469: iload 15
    //   471: invokevirtual 289	org/json/JSONArray:get	(I)Ljava/lang/Object;
    //   474: checkcast 291	org/json/JSONObject
    //   477: astore 28
    //   479: aload 28
    //   481: ldc_w 293
    //   484: invokevirtual 296	org/json/JSONObject:get	(Ljava/lang/String;)Ljava/lang/Object;
    //   487: checkcast 33	java/lang/String
    //   490: astore 29
    //   492: aload 29
    //   494: invokestatic 301	com/sohu/app/ads/sdk/f/d:a	(Ljava/lang/String;)Z
    //   497: ifeq +13 -> 510
    //   500: aload 27
    //   502: aload 29
    //   504: invokestatic 222	java/lang/Integer:parseInt	(Ljava/lang/String;)I
    //   507: invokevirtual 303	com/sohu/app/ads/sdk/model/d:a	(I)V
    //   510: aload 28
    //   512: ldc_w 305
    //   515: invokevirtual 296	org/json/JSONObject:get	(Ljava/lang/String;)Ljava/lang/Object;
    //   518: checkcast 33	java/lang/String
    //   521: astore 30
    //   523: aload 30
    //   525: invokestatic 301	com/sohu/app/ads/sdk/f/d:a	(Ljava/lang/String;)Z
    //   528: ifeq +10 -> 538
    //   531: aload 27
    //   533: aload 30
    //   535: invokevirtual 307	com/sohu/app/ads/sdk/model/d:a	(Ljava/lang/String;)V
    //   538: aload 28
    //   540: ldc_w 309
    //   543: invokevirtual 296	org/json/JSONObject:get	(Ljava/lang/String;)Ljava/lang/Object;
    //   546: checkcast 33	java/lang/String
    //   549: astore 31
    //   551: aload 31
    //   553: invokestatic 301	com/sohu/app/ads/sdk/f/d:a	(Ljava/lang/String;)Z
    //   556: ifeq +10 -> 566
    //   559: aload 27
    //   561: aload 31
    //   563: invokevirtual 311	com/sohu/app/ads/sdk/model/d:b	(Ljava/lang/String;)V
    //   566: aload 9
    //   568: invokevirtual 161	com/sohu/app/ads/sdk/model/AdsResponse:getSdkTracking	()Ljava/util/ArrayList;
    //   571: aload 27
    //   573: invokevirtual 213	java/util/ArrayList:add	(Ljava/lang/Object;)Z
    //   576: pop
    //   577: iinc 15 1
    //   580: goto -132 -> 448
    //   583: astore 11
    //   585: aload 11
    //   587: invokevirtual 314	java/lang/Exception:printStackTrace	()V
    //   590: goto -413 -> 177
    //   593: astore 7
    //   595: aload 7
    //   597: invokevirtual 61	java/lang/Exception:toString	()Ljava/lang/String;
    //   600: invokestatic 67	com/sohu/app/ads/sdk/c/a:c	(Ljava/lang/String;)V
    //   603: aload 4
    //   605: invokevirtual 56	android/database/sqlite/SQLiteDatabase:endTransaction	()V
    //   608: aload 4
    //   610: invokevirtual 57	android/database/sqlite/SQLiteDatabase:close	()V
    //   613: ldc 2
    //   615: monitorexit
    //   616: aload_0
    //   617: monitorexit
    //   618: aload 5
    //   620: areturn
    //   621: astore 12
    //   623: aload 12
    //   625: invokevirtual 314	java/lang/Exception:printStackTrace	()V
    //   628: goto -427 -> 201
    //   631: astore 6
    //   633: aload 4
    //   635: invokevirtual 56	android/database/sqlite/SQLiteDatabase:endTransaction	()V
    //   638: aload 6
    //   640: athrow
    //   641: astore_3
    //   642: ldc 2
    //   644: monitorexit
    //   645: aload_3
    //   646: athrow
    //   647: astore_2
    //   648: aload_0
    //   649: monitorexit
    //   650: aload_2
    //   651: athrow
    //   652: astore 16
    //   654: aload 16
    //   656: invokevirtual 314	java/lang/Exception:printStackTrace	()V
    //   659: aload 8
    //   661: aload 8
    //   663: ldc_w 316
    //   666: invokeinterface 190 2 0
    //   671: invokeinterface 205 2 0
    //   676: astore 17
    //   678: new 279	org/json/JSONArray
    //   681: dup
    //   682: aload 17
    //   684: invokespecial 281	org/json/JSONArray:<init>	(Ljava/lang/String;)V
    //   687: astore 18
    //   689: iconst_0
    //   690: istore 19
    //   692: iload 19
    //   694: aload 18
    //   696: invokevirtual 282	org/json/JSONArray:length	()I
    //   699: if_icmpge +104 -> 803
    //   702: new 318	com/sohu/app/ads/sdk/model/c
    //   705: dup
    //   706: invokespecial 319	com/sohu/app/ads/sdk/model/c:<init>	()V
    //   709: astore 22
    //   711: aload 18
    //   713: iload 19
    //   715: invokevirtual 289	org/json/JSONArray:get	(I)Ljava/lang/Object;
    //   718: checkcast 291	org/json/JSONObject
    //   721: astore 23
    //   723: aload 23
    //   725: ldc_w 305
    //   728: invokevirtual 296	org/json/JSONObject:get	(Ljava/lang/String;)Ljava/lang/Object;
    //   731: checkcast 33	java/lang/String
    //   734: astore 24
    //   736: aload 24
    //   738: invokestatic 301	com/sohu/app/ads/sdk/f/d:a	(Ljava/lang/String;)Z
    //   741: ifeq +10 -> 751
    //   744: aload 22
    //   746: aload 24
    //   748: invokevirtual 320	com/sohu/app/ads/sdk/model/c:a	(Ljava/lang/String;)V
    //   751: aload 23
    //   753: ldc_w 309
    //   756: invokevirtual 296	org/json/JSONObject:get	(Ljava/lang/String;)Ljava/lang/Object;
    //   759: checkcast 33	java/lang/String
    //   762: astore 25
    //   764: aload 25
    //   766: invokestatic 301	com/sohu/app/ads/sdk/f/d:a	(Ljava/lang/String;)Z
    //   769: ifeq +10 -> 779
    //   772: aload 22
    //   774: aload 25
    //   776: invokevirtual 321	com/sohu/app/ads/sdk/model/c:b	(Ljava/lang/String;)V
    //   779: aload 9
    //   781: invokevirtual 165	com/sohu/app/ads/sdk/model/AdsResponse:getSdkClickTracking	()Ljava/util/ArrayList;
    //   784: aload 22
    //   786: invokevirtual 213	java/util/ArrayList:add	(Ljava/lang/Object;)Z
    //   789: pop
    //   790: iinc 19 1
    //   793: goto -101 -> 692
    //   796: astore 20
    //   798: aload 20
    //   800: invokevirtual 314	java/lang/Exception:printStackTrace	()V
    //   803: aload 5
    //   805: aload 9
    //   807: invokevirtual 213	java/util/ArrayList:add	(Ljava/lang/Object;)Z
    //   810: pop
    //   811: goto -767 -> 44
    //   814: aload 8
    //   816: invokeinterface 50 1 0
    //   821: aload 4
    //   823: invokevirtual 53	android/database/sqlite/SQLiteDatabase:setTransactionSuccessful	()V
    //   826: aload 4
    //   828: invokevirtual 56	android/database/sqlite/SQLiteDatabase:endTransaction	()V
    //   831: goto -223 -> 608
    //
    // Exception table:
    //   from	to	target	type
    //   114	137	583	java/lang/Exception
    //   145	164	583	java/lang/Exception
    //   170	177	583	java/lang/Exception
    //   27	44	593	java/lang/Exception
    //   44	114	593	java/lang/Exception
    //   201	434	593	java/lang/Exception
    //   585	590	593	java/lang/Exception
    //   623	628	593	java/lang/Exception
    //   654	659	593	java/lang/Exception
    //   659	678	593	java/lang/Exception
    //   798	803	593	java/lang/Exception
    //   803	811	593	java/lang/Exception
    //   814	826	593	java/lang/Exception
    //   177	201	621	java/lang/Exception
    //   27	44	631	finally
    //   44	114	631	finally
    //   114	137	631	finally
    //   145	164	631	finally
    //   170	177	631	finally
    //   177	201	631	finally
    //   201	434	631	finally
    //   434	445	631	finally
    //   448	510	631	finally
    //   510	538	631	finally
    //   538	566	631	finally
    //   566	577	631	finally
    //   585	590	631	finally
    //   595	603	631	finally
    //   623	628	631	finally
    //   654	659	631	finally
    //   659	678	631	finally
    //   678	689	631	finally
    //   692	751	631	finally
    //   751	779	631	finally
    //   779	790	631	finally
    //   798	803	631	finally
    //   803	811	631	finally
    //   814	826	631	finally
    //   5	27	641	finally
    //   603	608	641	finally
    //   608	616	641	finally
    //   633	641	641	finally
    //   642	645	641	finally
    //   826	831	641	finally
    //   2	5	647	finally
    //   645	647	647	finally
    //   434	445	652	java/lang/Exception
    //   448	510	652	java/lang/Exception
    //   510	538	652	java/lang/Exception
    //   538	566	652	java/lang/Exception
    //   566	577	652	java/lang/Exception
    //   678	689	796	java/lang/Exception
    //   692	751	796	java/lang/Exception
    //   751	779	796	java/lang/Exception
    //   779	790	796	java/lang/Exception
  }

  // ERROR //
  public void b(java.lang.String paramString1, java.lang.String paramString2)
  {
    // Byte code:
    //   0: aload_0
    //   1: monitorenter
    //   2: ldc 2
    //   4: monitorenter
    //   5: getstatic 17	com/sohu/app/ads/sdk/a/c:a	Lcom/sohu/app/ads/sdk/a/a;
    //   8: invokevirtual 70	com/sohu/app/ads/sdk/a/a:getWritableDatabase	()Landroid/database/sqlite/SQLiteDatabase;
    //   11: astore 5
    //   13: aload 5
    //   15: invokevirtual 29	android/database/sqlite/SQLiteDatabase:beginTransaction	()V
    //   18: aload 5
    //   20: ldc_w 324
    //   23: iconst_2
    //   24: anewarray 33	java/lang/String
    //   27: dup
    //   28: iconst_0
    //   29: aload_1
    //   30: aastore
    //   31: dup
    //   32: iconst_1
    //   33: aload_2
    //   34: aastore
    //   35: invokevirtual 76	android/database/sqlite/SQLiteDatabase:execSQL	(Ljava/lang/String;[Ljava/lang/Object;)V
    //   38: aload 5
    //   40: invokevirtual 53	android/database/sqlite/SQLiteDatabase:setTransactionSuccessful	()V
    //   43: aload 5
    //   45: invokevirtual 56	android/database/sqlite/SQLiteDatabase:endTransaction	()V
    //   48: aload 5
    //   50: invokevirtual 57	android/database/sqlite/SQLiteDatabase:close	()V
    //   53: ldc 2
    //   55: monitorexit
    //   56: aload_0
    //   57: monitorexit
    //   58: return
    //   59: astore 7
    //   61: aload 7
    //   63: invokevirtual 61	java/lang/Exception:toString	()Ljava/lang/String;
    //   66: invokestatic 67	com/sohu/app/ads/sdk/c/a:c	(Ljava/lang/String;)V
    //   69: aload 5
    //   71: invokevirtual 56	android/database/sqlite/SQLiteDatabase:endTransaction	()V
    //   74: goto -26 -> 48
    //   77: astore 4
    //   79: ldc 2
    //   81: monitorexit
    //   82: aload 4
    //   84: athrow
    //   85: astore_3
    //   86: aload_0
    //   87: monitorexit
    //   88: aload_3
    //   89: athrow
    //   90: astore 6
    //   92: aload 5
    //   94: invokevirtual 56	android/database/sqlite/SQLiteDatabase:endTransaction	()V
    //   97: aload 6
    //   99: athrow
    //
    // Exception table:
    //   from	to	target	type
    //   18	43	59	java/lang/Exception
    //   5	18	77	finally
    //   43	48	77	finally
    //   48	56	77	finally
    //   69	74	77	finally
    //   79	82	77	finally
    //   92	100	77	finally
    //   2	5	85	finally
    //   82	85	85	finally
    //   18	43	90	finally
    //   61	69	90	finally
  }
}

/* Location:           C:\Users\THX\Desktop\aa\aa\反编译工具包\out\classes_dex2jar.jar
 * Qualified Name:     com.sohu.app.ads.sdk.a.c
 * JD-Core Version:    0.6.2
 */