package com.miaozhen.mzmonitor;

import android.content.Context;

class r extends Thread
{
  r(Context paramContext)
  {
  }

  // ERROR //
  public void run()
  {
    // Byte code:
    //   0: aconst_null
    //   1: astore_1
    //   2: invokestatic 24	com/miaozhen/mzmonitor/MZSdkProfile:access$0	()Ljava/lang/Thread;
    //   5: astore_2
    //   6: aload_2
    //   7: monitorenter
    //   8: aload_0
    //   9: getfield 10	com/miaozhen/mzmonitor/r:a	Landroid/content/Context;
    //   12: ldc 26
    //   14: iconst_0
    //   15: invokevirtual 32	android/content/Context:getSharedPreferences	(Ljava/lang/String;I)Landroid/content/SharedPreferences;
    //   18: astore 10
    //   20: new 34	java/net/URL
    //   23: dup
    //   24: aload 10
    //   26: ldc 36
    //   28: ldc 38
    //   30: invokeinterface 44 3 0
    //   35: invokespecial 47	java/net/URL:<init>	(Ljava/lang/String;)V
    //   38: invokevirtual 51	java/net/URL:openConnection	()Ljava/net/URLConnection;
    //   41: checkcast 53	java/net/HttpURLConnection
    //   44: astore 11
    //   46: aload 11
    //   48: sipush 5000
    //   51: invokevirtual 57	java/net/HttpURLConnection:setConnectTimeout	(I)V
    //   54: aload 11
    //   56: iconst_0
    //   57: invokevirtual 61	java/net/HttpURLConnection:setUseCaches	(Z)V
    //   60: aload 11
    //   62: ldc 63
    //   64: invokevirtual 66	java/net/HttpURLConnection:setRequestMethod	(Ljava/lang/String;)V
    //   67: aload 11
    //   69: invokevirtual 69	java/net/HttpURLConnection:connect	()V
    //   72: aload 11
    //   74: invokevirtual 73	java/net/HttpURLConnection:getResponseCode	()I
    //   77: ifle +297 -> 374
    //   80: aload 11
    //   82: invokevirtual 73	java/net/HttpURLConnection:getResponseCode	()I
    //   85: sipush 400
    //   88: if_icmpge +286 -> 374
    //   91: aload 11
    //   93: invokevirtual 77	java/net/HttpURLConnection:getInputStream	()Ljava/io/InputStream;
    //   96: astore 15
    //   98: aload 15
    //   100: astore 13
    //   102: new 79	java/io/BufferedReader
    //   105: dup
    //   106: new 81	java/io/InputStreamReader
    //   109: dup
    //   110: aload 13
    //   112: invokespecial 84	java/io/InputStreamReader:<init>	(Ljava/io/InputStream;)V
    //   115: invokespecial 87	java/io/BufferedReader:<init>	(Ljava/io/Reader;)V
    //   118: astore 4
    //   120: new 89	java/lang/StringBuffer
    //   123: dup
    //   124: invokespecial 90	java/lang/StringBuffer:<init>	()V
    //   127: astore 16
    //   129: aload 4
    //   131: invokevirtual 94	java/io/BufferedReader:readLine	()Ljava/lang/String;
    //   134: astore 17
    //   136: aload 17
    //   138: ifnonnull +72 -> 210
    //   141: aload 10
    //   143: invokeinterface 98 1 0
    //   148: ldc 100
    //   150: aload 16
    //   152: invokevirtual 103	java/lang/StringBuffer:toString	()Ljava/lang/String;
    //   155: invokeinterface 109 3 0
    //   160: invokeinterface 113 1 0
    //   165: pop
    //   166: aload_0
    //   167: getfield 10	com/miaozhen/mzmonitor/r:a	Landroid/content/Context;
    //   170: invokestatic 116	com/miaozhen/mzmonitor/MZSdkProfile:updateLocalProfileByConfig	(Landroid/content/Context;)V
    //   173: aload_0
    //   174: getfield 10	com/miaozhen/mzmonitor/r:a	Landroid/content/Context;
    //   177: invokestatic 121	com/miaozhen/mzmonitor/d:a	(Landroid/content/Context;)Lcom/miaozhen/mzmonitor/d;
    //   180: invokevirtual 124	com/miaozhen/mzmonitor/d:b	()V
    //   183: aload 4
    //   185: astore 12
    //   187: aload 13
    //   189: ifnull +8 -> 197
    //   192: aload 13
    //   194: invokevirtual 129	java/io/InputStream:close	()V
    //   197: aload 12
    //   199: ifnull +8 -> 207
    //   202: aload 12
    //   204: invokevirtual 130	java/io/BufferedReader:close	()V
    //   207: aload_2
    //   208: monitorexit
    //   209: return
    //   210: aload 16
    //   212: aload 17
    //   214: invokevirtual 134	java/lang/StringBuffer:append	(Ljava/lang/String;)Ljava/lang/StringBuffer;
    //   217: pop
    //   218: goto -89 -> 129
    //   221: astore_3
    //   222: aload 13
    //   224: astore_1
    //   225: ldc 136
    //   227: new 138	java/lang/StringBuilder
    //   230: dup
    //   231: ldc 140
    //   233: invokespecial 141	java/lang/StringBuilder:<init>	(Ljava/lang/String;)V
    //   236: aload_3
    //   237: invokevirtual 144	java/lang/StringBuilder:append	(Ljava/lang/Object;)Ljava/lang/StringBuilder;
    //   240: invokevirtual 145	java/lang/StringBuilder:toString	()Ljava/lang/String;
    //   243: invokestatic 151	android/util/Log:d	(Ljava/lang/String;Ljava/lang/String;)I
    //   246: pop
    //   247: aload_1
    //   248: ifnull +7 -> 255
    //   251: aload_1
    //   252: invokevirtual 129	java/io/InputStream:close	()V
    //   255: aload 4
    //   257: ifnull -50 -> 207
    //   260: aload 4
    //   262: invokevirtual 130	java/io/BufferedReader:close	()V
    //   265: goto -58 -> 207
    //   268: astore 9
    //   270: aload 9
    //   272: invokevirtual 154	java/io/IOException:printStackTrace	()V
    //   275: goto -68 -> 207
    //   278: astore 7
    //   280: aload_2
    //   281: monitorexit
    //   282: aload 7
    //   284: athrow
    //   285: astore 5
    //   287: aconst_null
    //   288: astore 4
    //   290: aload_1
    //   291: ifnull +7 -> 298
    //   294: aload_1
    //   295: invokevirtual 129	java/io/InputStream:close	()V
    //   298: aload 4
    //   300: ifnull +8 -> 308
    //   303: aload 4
    //   305: invokevirtual 130	java/io/BufferedReader:close	()V
    //   308: aload 5
    //   310: athrow
    //   311: astore 6
    //   313: aload 6
    //   315: invokevirtual 154	java/io/IOException:printStackTrace	()V
    //   318: goto -10 -> 308
    //   321: astore 14
    //   323: aload 14
    //   325: invokevirtual 154	java/io/IOException:printStackTrace	()V
    //   328: goto -121 -> 207
    //   331: astore 5
    //   333: aload 13
    //   335: astore_1
    //   336: aconst_null
    //   337: astore 4
    //   339: goto -49 -> 290
    //   342: astore 5
    //   344: aload 13
    //   346: astore_1
    //   347: goto -57 -> 290
    //   350: astore 5
    //   352: goto -62 -> 290
    //   355: astore_3
    //   356: aconst_null
    //   357: astore 4
    //   359: aconst_null
    //   360: astore_1
    //   361: goto -136 -> 225
    //   364: astore_3
    //   365: aload 13
    //   367: astore_1
    //   368: aconst_null
    //   369: astore 4
    //   371: goto -146 -> 225
    //   374: aconst_null
    //   375: astore 12
    //   377: aconst_null
    //   378: astore 13
    //   380: goto -193 -> 187
    //
    // Exception table:
    //   from	to	target	type
    //   120	129	221	java/lang/Exception
    //   129	136	221	java/lang/Exception
    //   141	183	221	java/lang/Exception
    //   210	218	221	java/lang/Exception
    //   251	255	268	java/io/IOException
    //   260	265	268	java/io/IOException
    //   192	197	278	finally
    //   202	207	278	finally
    //   207	209	278	finally
    //   251	255	278	finally
    //   260	265	278	finally
    //   270	275	278	finally
    //   280	282	278	finally
    //   294	298	278	finally
    //   303	308	278	finally
    //   308	311	278	finally
    //   313	318	278	finally
    //   323	328	278	finally
    //   8	98	285	finally
    //   294	298	311	java/io/IOException
    //   303	308	311	java/io/IOException
    //   192	197	321	java/io/IOException
    //   202	207	321	java/io/IOException
    //   102	120	331	finally
    //   120	129	342	finally
    //   129	136	342	finally
    //   141	183	342	finally
    //   210	218	342	finally
    //   225	247	350	finally
    //   8	98	355	java/lang/Exception
    //   102	120	364	java/lang/Exception
  }
}

/* Location:           C:\Users\THX\Desktop\aa\aa\反编译工具包\out\classes_dex2jar.jar
 * Qualified Name:     com.miaozhen.mzmonitor.r
 * JD-Core Version:    0.6.2
 */