package com.starcor.core.parser.json;

import com.starcor.core.domain.AssetCategoryCountStruct;
import com.starcor.core.domain.SearchListItem;
import com.starcor.core.domain.SearchStruct;
import com.starcor.core.interfaces.IXmlParser;
import java.io.InputStream;
import java.util.ArrayList;

public class SearchMediaAssetsItemSAXParserJson<Result>
  implements IXmlParser<Result>
{
  private static final String TAG = "SearchMediaAssetsItemSAXParserJson";
  private AssetCategoryCountStruct assetInfo;
  private SearchListItem fItem;
  private SearchStruct sInfo = new SearchStruct();

  public SearchMediaAssetsItemSAXParserJson()
  {
    this.sInfo.sItemList = new ArrayList();
  }

  public Result parser(InputStream paramInputStream)
  {
    return null;
  }

  // ERROR //
  public Result parser(byte[] paramArrayOfByte)
  {
    // Byte code:
    //   0: aload_1
    //   1: ifnonnull +5 -> 6
    //   4: aconst_null
    //   5: areturn
    //   6: new 40	java/lang/String
    //   9: dup
    //   10: aload_1
    //   11: invokespecial 43	java/lang/String:<init>	([B)V
    //   14: invokestatic 49	com/starcor/core/utils/JsonUtils:getJsonObject	(Ljava/lang/String;)Lorg/json/JSONObject;
    //   17: astore_3
    //   18: aload_0
    //   19: getfield 26	com/starcor/core/parser/json/SearchMediaAssetsItemSAXParserJson:sInfo	Lcom/starcor/core/domain/SearchStruct;
    //   22: aload_3
    //   23: ldc 51
    //   25: iconst_0
    //   26: invokevirtual 57	org/json/JSONObject:optInt	(Ljava/lang/String;I)I
    //   29: putfield 61	com/starcor/core/domain/SearchStruct:item_num	I
    //   32: aload_0
    //   33: getfield 26	com/starcor/core/parser/json/SearchMediaAssetsItemSAXParserJson:sInfo	Lcom/starcor/core/domain/SearchStruct;
    //   36: aload_3
    //   37: ldc 63
    //   39: iconst_0
    //   40: invokevirtual 57	org/json/JSONObject:optInt	(Ljava/lang/String;I)I
    //   43: putfield 66	com/starcor/core/domain/SearchStruct:asset_pages_count	I
    //   46: aload_0
    //   47: getfield 26	com/starcor/core/parser/json/SearchMediaAssetsItemSAXParserJson:sInfo	Lcom/starcor/core/domain/SearchStruct;
    //   50: aload_3
    //   51: ldc 68
    //   53: iconst_0
    //   54: invokevirtual 57	org/json/JSONObject:optInt	(Ljava/lang/String;I)I
    //   57: putfield 71	com/starcor/core/domain/SearchStruct:cur_page	I
    //   60: aload_3
    //   61: ldc 73
    //   63: invokevirtual 77	org/json/JSONObject:has	(Ljava/lang/String;)Z
    //   66: ifeq +118 -> 184
    //   69: aload_0
    //   70: new 79	com/starcor/core/domain/AssetCategoryCountStruct
    //   73: dup
    //   74: invokespecial 80	com/starcor/core/domain/AssetCategoryCountStruct:<init>	()V
    //   77: putfield 82	com/starcor/core/parser/json/SearchMediaAssetsItemSAXParserJson:assetInfo	Lcom/starcor/core/domain/AssetCategoryCountStruct;
    //   80: new 53	org/json/JSONObject
    //   83: dup
    //   84: aload_3
    //   85: ldc 73
    //   87: invokevirtual 86	org/json/JSONObject:getString	(Ljava/lang/String;)Ljava/lang/String;
    //   90: invokespecial 89	org/json/JSONObject:<init>	(Ljava/lang/String;)V
    //   93: astore 17
    //   95: aload 17
    //   97: ldc 91
    //   99: invokevirtual 77	org/json/JSONObject:has	(Ljava/lang/String;)Z
    //   102: ifeq +17 -> 119
    //   105: aload_0
    //   106: getfield 82	com/starcor/core/parser/json/SearchMediaAssetsItemSAXParserJson:assetInfo	Lcom/starcor/core/domain/AssetCategoryCountStruct;
    //   109: aload 17
    //   111: ldc 91
    //   113: invokevirtual 86	org/json/JSONObject:getString	(Ljava/lang/String;)Ljava/lang/String;
    //   116: putfield 93	com/starcor/core/domain/AssetCategoryCountStruct:media_assets_id	Ljava/lang/String;
    //   119: aload 17
    //   121: ldc 95
    //   123: invokevirtual 77	org/json/JSONObject:has	(Ljava/lang/String;)Z
    //   126: ifeq +17 -> 143
    //   129: aload_0
    //   130: getfield 82	com/starcor/core/parser/json/SearchMediaAssetsItemSAXParserJson:assetInfo	Lcom/starcor/core/domain/AssetCategoryCountStruct;
    //   133: aload 17
    //   135: ldc 95
    //   137: invokevirtual 86	org/json/JSONObject:getString	(Ljava/lang/String;)Ljava/lang/String;
    //   140: putfield 98	com/starcor/core/domain/AssetCategoryCountStruct:category_id	Ljava/lang/String;
    //   143: aload 17
    //   145: ldc 100
    //   147: invokevirtual 77	org/json/JSONObject:has	(Ljava/lang/String;)Z
    //   150: ifeq +23 -> 173
    //   153: aload_0
    //   154: getfield 82	com/starcor/core/parser/json/SearchMediaAssetsItemSAXParserJson:assetInfo	Lcom/starcor/core/domain/AssetCategoryCountStruct;
    //   157: aload 17
    //   159: ldc 100
    //   161: invokevirtual 86	org/json/JSONObject:getString	(Ljava/lang/String;)Ljava/lang/String;
    //   164: invokestatic 106	java/lang/Integer:valueOf	(Ljava/lang/String;)Ljava/lang/Integer;
    //   167: invokevirtual 110	java/lang/Integer:intValue	()I
    //   170: putfield 112	com/starcor/core/domain/AssetCategoryCountStruct:count	I
    //   173: aload_0
    //   174: getfield 26	com/starcor/core/parser/json/SearchMediaAssetsItemSAXParserJson:sInfo	Lcom/starcor/core/domain/SearchStruct;
    //   177: aload_0
    //   178: getfield 82	com/starcor/core/parser/json/SearchMediaAssetsItemSAXParserJson:assetInfo	Lcom/starcor/core/domain/AssetCategoryCountStruct;
    //   181: putfield 115	com/starcor/core/domain/SearchStruct:asset_category_count	Lcom/starcor/core/domain/AssetCategoryCountStruct;
    //   184: aload_3
    //   185: ldc 117
    //   187: invokevirtual 77	org/json/JSONObject:has	(Ljava/lang/String;)Z
    //   190: ifeq +644 -> 834
    //   193: aload_3
    //   194: ldc 117
    //   196: invokevirtual 121	org/json/JSONObject:getJSONArray	(Ljava/lang/String;)Lorg/json/JSONArray;
    //   199: astore 5
    //   201: iconst_0
    //   202: istore 6
    //   204: iload 6
    //   206: aload 5
    //   208: invokevirtual 126	org/json/JSONArray:length	()I
    //   211: if_icmpge +623 -> 834
    //   214: aload_0
    //   215: new 128	com/starcor/core/domain/SearchListItem
    //   218: dup
    //   219: invokespecial 129	com/starcor/core/domain/SearchListItem:<init>	()V
    //   222: putfield 131	com/starcor/core/parser/json/SearchMediaAssetsItemSAXParserJson:fItem	Lcom/starcor/core/domain/SearchListItem;
    //   225: aload 5
    //   227: iload 6
    //   229: invokevirtual 135	org/json/JSONArray:getJSONObject	(I)Lorg/json/JSONObject;
    //   232: astore 7
    //   234: aload 7
    //   236: ldc 137
    //   238: invokevirtual 77	org/json/JSONObject:has	(Ljava/lang/String;)Z
    //   241: ifeq +17 -> 258
    //   244: aload_0
    //   245: getfield 131	com/starcor/core/parser/json/SearchMediaAssetsItemSAXParserJson:fItem	Lcom/starcor/core/domain/SearchListItem;
    //   248: aload 7
    //   250: ldc 137
    //   252: invokevirtual 86	org/json/JSONObject:getString	(Ljava/lang/String;)Ljava/lang/String;
    //   255: putfield 140	com/starcor/core/domain/SearchListItem:item_id	Ljava/lang/String;
    //   258: aload 7
    //   260: ldc 142
    //   262: invokevirtual 77	org/json/JSONObject:has	(Ljava/lang/String;)Z
    //   265: ifeq +17 -> 282
    //   268: aload_0
    //   269: getfield 131	com/starcor/core/parser/json/SearchMediaAssetsItemSAXParserJson:fItem	Lcom/starcor/core/domain/SearchListItem;
    //   272: aload 7
    //   274: ldc 142
    //   276: invokevirtual 86	org/json/JSONObject:getString	(Ljava/lang/String;)Ljava/lang/String;
    //   279: putfield 145	com/starcor/core/domain/SearchListItem:import_id	Ljava/lang/String;
    //   282: aload 7
    //   284: ldc 147
    //   286: invokevirtual 77	org/json/JSONObject:has	(Ljava/lang/String;)Z
    //   289: ifeq +17 -> 306
    //   292: aload_0
    //   293: getfield 131	com/starcor/core/parser/json/SearchMediaAssetsItemSAXParserJson:fItem	Lcom/starcor/core/domain/SearchListItem;
    //   296: aload 7
    //   298: ldc 147
    //   300: invokevirtual 86	org/json/JSONObject:getString	(Ljava/lang/String;)Ljava/lang/String;
    //   303: putfield 150	com/starcor/core/domain/SearchListItem:serial_id	Ljava/lang/String;
    //   306: aload 7
    //   308: ldc 152
    //   310: invokevirtual 77	org/json/JSONObject:has	(Ljava/lang/String;)Z
    //   313: ifeq +17 -> 330
    //   316: aload_0
    //   317: getfield 131	com/starcor/core/parser/json/SearchMediaAssetsItemSAXParserJson:fItem	Lcom/starcor/core/domain/SearchListItem;
    //   320: aload 7
    //   322: ldc 152
    //   324: invokevirtual 86	org/json/JSONObject:getString	(Ljava/lang/String;)Ljava/lang/String;
    //   327: putfield 154	com/starcor/core/domain/SearchListItem:name	Ljava/lang/String;
    //   330: aload 7
    //   332: ldc 156
    //   334: invokevirtual 77	org/json/JSONObject:has	(Ljava/lang/String;)Z
    //   337: ifeq +17 -> 354
    //   340: aload_0
    //   341: getfield 131	com/starcor/core/parser/json/SearchMediaAssetsItemSAXParserJson:fItem	Lcom/starcor/core/domain/SearchListItem;
    //   344: aload 7
    //   346: ldc 156
    //   348: invokevirtual 86	org/json/JSONObject:getString	(Ljava/lang/String;)Ljava/lang/String;
    //   351: putfield 159	com/starcor/core/domain/SearchListItem:big_img_url	Ljava/lang/String;
    //   354: aload 7
    //   356: ldc 161
    //   358: invokevirtual 77	org/json/JSONObject:has	(Ljava/lang/String;)Z
    //   361: ifeq +17 -> 378
    //   364: aload_0
    //   365: getfield 131	com/starcor/core/parser/json/SearchMediaAssetsItemSAXParserJson:fItem	Lcom/starcor/core/domain/SearchListItem;
    //   368: aload 7
    //   370: ldc 161
    //   372: invokevirtual 86	org/json/JSONObject:getString	(Ljava/lang/String;)Ljava/lang/String;
    //   375: putfield 164	com/starcor/core/domain/SearchListItem:normal_img_url	Ljava/lang/String;
    //   378: aload 7
    //   380: ldc 166
    //   382: invokevirtual 77	org/json/JSONObject:has	(Ljava/lang/String;)Z
    //   385: ifeq +17 -> 402
    //   388: aload_0
    //   389: getfield 131	com/starcor/core/parser/json/SearchMediaAssetsItemSAXParserJson:fItem	Lcom/starcor/core/domain/SearchListItem;
    //   392: aload 7
    //   394: ldc 166
    //   396: invokevirtual 86	org/json/JSONObject:getString	(Ljava/lang/String;)Ljava/lang/String;
    //   399: putfield 169	com/starcor/core/domain/SearchListItem:small_img_url	Ljava/lang/String;
    //   402: aload 7
    //   404: ldc 171
    //   406: invokevirtual 77	org/json/JSONObject:has	(Ljava/lang/String;)Z
    //   409: ifeq +17 -> 426
    //   412: aload_0
    //   413: getfield 131	com/starcor/core/parser/json/SearchMediaAssetsItemSAXParserJson:fItem	Lcom/starcor/core/domain/SearchListItem;
    //   416: aload 7
    //   418: ldc 171
    //   420: invokevirtual 86	org/json/JSONObject:getString	(Ljava/lang/String;)Ljava/lang/String;
    //   423: putfield 173	com/starcor/core/domain/SearchListItem:video_id	Ljava/lang/String;
    //   426: aload 7
    //   428: ldc 175
    //   430: invokevirtual 77	org/json/JSONObject:has	(Ljava/lang/String;)Z
    //   433: ifeq +23 -> 456
    //   436: aload_0
    //   437: getfield 131	com/starcor/core/parser/json/SearchMediaAssetsItemSAXParserJson:fItem	Lcom/starcor/core/domain/SearchListItem;
    //   440: aload 7
    //   442: ldc 175
    //   444: invokevirtual 86	org/json/JSONObject:getString	(Ljava/lang/String;)Ljava/lang/String;
    //   447: invokestatic 106	java/lang/Integer:valueOf	(Ljava/lang/String;)Ljava/lang/Integer;
    //   450: invokevirtual 110	java/lang/Integer:intValue	()I
    //   453: putfield 177	com/starcor/core/domain/SearchListItem:video_type	I
    //   456: aload 7
    //   458: ldc 179
    //   460: invokevirtual 77	org/json/JSONObject:has	(Ljava/lang/String;)Z
    //   463: ifeq +23 -> 486
    //   466: aload_0
    //   467: getfield 131	com/starcor/core/parser/json/SearchMediaAssetsItemSAXParserJson:fItem	Lcom/starcor/core/domain/SearchListItem;
    //   470: aload 7
    //   472: ldc 179
    //   474: invokevirtual 86	org/json/JSONObject:getString	(Ljava/lang/String;)Ljava/lang/String;
    //   477: invokestatic 106	java/lang/Integer:valueOf	(Ljava/lang/String;)Ljava/lang/Integer;
    //   480: invokevirtual 110	java/lang/Integer:intValue	()I
    //   483: putfield 181	com/starcor/core/domain/SearchListItem:ui_style	I
    //   486: aload 7
    //   488: ldc 183
    //   490: invokevirtual 77	org/json/JSONObject:has	(Ljava/lang/String;)Z
    //   493: ifeq +23 -> 516
    //   496: aload_0
    //   497: getfield 131	com/starcor/core/parser/json/SearchMediaAssetsItemSAXParserJson:fItem	Lcom/starcor/core/domain/SearchListItem;
    //   500: aload 7
    //   502: ldc 183
    //   504: invokevirtual 86	org/json/JSONObject:getString	(Ljava/lang/String;)Ljava/lang/String;
    //   507: invokestatic 106	java/lang/Integer:valueOf	(Ljava/lang/String;)Ljava/lang/Integer;
    //   510: invokevirtual 110	java/lang/Integer:intValue	()I
    //   513: putfield 185	com/starcor/core/domain/SearchListItem:play_count	I
    //   516: aload 7
    //   518: ldc 187
    //   520: invokevirtual 77	org/json/JSONObject:has	(Ljava/lang/String;)Z
    //   523: ifeq +28 -> 551
    //   526: aload 7
    //   528: ldc 187
    //   530: invokevirtual 86	org/json/JSONObject:getString	(Ljava/lang/String;)Ljava/lang/String;
    //   533: invokestatic 192	java/lang/Float:valueOf	(Ljava/lang/String;)Ljava/lang/Float;
    //   536: invokevirtual 196	java/lang/Float:floatValue	()F
    //   539: fstore 16
    //   541: aload_0
    //   542: getfield 131	com/starcor/core/parser/json/SearchMediaAssetsItemSAXParserJson:fItem	Lcom/starcor/core/domain/SearchListItem;
    //   545: fload 16
    //   547: f2i
    //   548: putfield 198	com/starcor/core/domain/SearchListItem:user_score	I
    //   551: aload 7
    //   553: ldc 200
    //   555: invokevirtual 77	org/json/JSONObject:has	(Ljava/lang/String;)Z
    //   558: ifeq +23 -> 581
    //   561: aload_0
    //   562: getfield 131	com/starcor/core/parser/json/SearchMediaAssetsItemSAXParserJson:fItem	Lcom/starcor/core/domain/SearchListItem;
    //   565: aload 7
    //   567: ldc 200
    //   569: invokevirtual 86	org/json/JSONObject:getString	(Ljava/lang/String;)Ljava/lang/String;
    //   572: invokestatic 106	java/lang/Integer:valueOf	(Ljava/lang/String;)Ljava/lang/Integer;
    //   575: invokevirtual 110	java/lang/Integer:intValue	()I
    //   578: putfield 202	com/starcor/core/domain/SearchListItem:point	I
    //   581: aload 7
    //   583: ldc 204
    //   585: invokevirtual 77	org/json/JSONObject:has	(Ljava/lang/String;)Z
    //   588: ifeq +17 -> 605
    //   591: aload_0
    //   592: getfield 131	com/starcor/core/parser/json/SearchMediaAssetsItemSAXParserJson:fItem	Lcom/starcor/core/domain/SearchListItem;
    //   595: aload 7
    //   597: ldc 204
    //   599: invokevirtual 86	org/json/JSONObject:getString	(Ljava/lang/String;)Ljava/lang/String;
    //   602: putfield 206	com/starcor/core/domain/SearchListItem:corner_mark	Ljava/lang/String;
    //   605: aload 7
    //   607: ldc 208
    //   609: invokevirtual 77	org/json/JSONObject:has	(Ljava/lang/String;)Z
    //   612: ifeq +17 -> 629
    //   615: aload_0
    //   616: getfield 131	com/starcor/core/parser/json/SearchMediaAssetsItemSAXParserJson:fItem	Lcom/starcor/core/domain/SearchListItem;
    //   619: aload 7
    //   621: ldc 208
    //   623: invokevirtual 86	org/json/JSONObject:getString	(Ljava/lang/String;)Ljava/lang/String;
    //   626: putfield 211	com/starcor/core/domain/SearchListItem:corner_mark_img_url	Ljava/lang/String;
    //   629: aload 7
    //   631: ldc 213
    //   633: invokevirtual 77	org/json/JSONObject:has	(Ljava/lang/String;)Z
    //   636: ifeq +23 -> 659
    //   639: aload_0
    //   640: getfield 131	com/starcor/core/parser/json/SearchMediaAssetsItemSAXParserJson:fItem	Lcom/starcor/core/domain/SearchListItem;
    //   643: aload 7
    //   645: ldc 213
    //   647: invokevirtual 86	org/json/JSONObject:getString	(Ljava/lang/String;)Ljava/lang/String;
    //   650: invokestatic 106	java/lang/Integer:valueOf	(Ljava/lang/String;)Ljava/lang/Integer;
    //   653: invokevirtual 110	java/lang/Integer:intValue	()I
    //   656: putfield 215	com/starcor/core/domain/SearchListItem:billing	I
    //   659: aload 7
    //   661: ldc 91
    //   663: invokevirtual 77	org/json/JSONObject:has	(Ljava/lang/String;)Z
    //   666: ifeq +17 -> 683
    //   669: aload_0
    //   670: getfield 131	com/starcor/core/parser/json/SearchMediaAssetsItemSAXParserJson:fItem	Lcom/starcor/core/domain/SearchListItem;
    //   673: aload 7
    //   675: ldc 91
    //   677: invokevirtual 86	org/json/JSONObject:getString	(Ljava/lang/String;)Ljava/lang/String;
    //   680: putfield 218	com/starcor/core/domain/SearchListItem:package_id	Ljava/lang/String;
    //   683: aload 7
    //   685: ldc 219
    //   687: invokevirtual 77	org/json/JSONObject:has	(Ljava/lang/String;)Z
    //   690: ifeq +17 -> 707
    //   693: aload_0
    //   694: getfield 131	com/starcor/core/parser/json/SearchMediaAssetsItemSAXParserJson:fItem	Lcom/starcor/core/domain/SearchListItem;
    //   697: aload 7
    //   699: ldc 219
    //   701: invokevirtual 86	org/json/JSONObject:getString	(Ljava/lang/String;)Ljava/lang/String;
    //   704: putfield 220	com/starcor/core/domain/SearchListItem:category_id	Ljava/lang/String;
    //   707: aload 7
    //   709: ldc 222
    //   711: invokevirtual 77	org/json/JSONObject:has	(Ljava/lang/String;)Z
    //   714: ifeq +17 -> 731
    //   717: aload_0
    //   718: getfield 131	com/starcor/core/parser/json/SearchMediaAssetsItemSAXParserJson:fItem	Lcom/starcor/core/domain/SearchListItem;
    //   721: aload 7
    //   723: ldc 222
    //   725: invokevirtual 86	org/json/JSONObject:getString	(Ljava/lang/String;)Ljava/lang/String;
    //   728: putfield 224	com/starcor/core/domain/SearchListItem:img_v	Ljava/lang/String;
    //   731: aload 7
    //   733: ldc 226
    //   735: invokevirtual 77	org/json/JSONObject:has	(Ljava/lang/String;)Z
    //   738: ifeq +17 -> 755
    //   741: aload_0
    //   742: getfield 131	com/starcor/core/parser/json/SearchMediaAssetsItemSAXParserJson:fItem	Lcom/starcor/core/domain/SearchListItem;
    //   745: aload 7
    //   747: ldc 226
    //   749: invokevirtual 86	org/json/JSONObject:getString	(Ljava/lang/String;)Ljava/lang/String;
    //   752: putfield 228	com/starcor/core/domain/SearchListItem:img_h	Ljava/lang/String;
    //   755: aload 7
    //   757: ldc 230
    //   759: invokevirtual 77	org/json/JSONObject:has	(Ljava/lang/String;)Z
    //   762: ifeq +17 -> 779
    //   765: aload_0
    //   766: getfield 131	com/starcor/core/parser/json/SearchMediaAssetsItemSAXParserJson:fItem	Lcom/starcor/core/domain/SearchListItem;
    //   769: aload 7
    //   771: ldc 230
    //   773: invokevirtual 86	org/json/JSONObject:getString	(Ljava/lang/String;)Ljava/lang/String;
    //   776: putfield 232	com/starcor/core/domain/SearchListItem:img_s	Ljava/lang/String;
    //   779: aload_0
    //   780: getfield 26	com/starcor/core/parser/json/SearchMediaAssetsItemSAXParserJson:sInfo	Lcom/starcor/core/domain/SearchStruct;
    //   783: getfield 33	com/starcor/core/domain/SearchStruct:sItemList	Ljava/util/ArrayList;
    //   786: aload_0
    //   787: getfield 131	com/starcor/core/parser/json/SearchMediaAssetsItemSAXParserJson:fItem	Lcom/starcor/core/domain/SearchListItem;
    //   790: invokevirtual 236	java/util/ArrayList:add	(Ljava/lang/Object;)Z
    //   793: pop
    //   794: iinc 6 1
    //   797: goto -593 -> 204
    //   800: astore 4
    //   802: aload 4
    //   804: invokevirtual 239	java/lang/Exception:printStackTrace	()V
    //   807: aload_0
    //   808: getfield 82	com/starcor/core/parser/json/SearchMediaAssetsItemSAXParserJson:assetInfo	Lcom/starcor/core/domain/AssetCategoryCountStruct;
    //   811: iconst_0
    //   812: putfield 112	com/starcor/core/domain/AssetCategoryCountStruct:count	I
    //   815: aload_0
    //   816: getfield 26	com/starcor/core/parser/json/SearchMediaAssetsItemSAXParserJson:sInfo	Lcom/starcor/core/domain/SearchStruct;
    //   819: aload_0
    //   820: getfield 82	com/starcor/core/parser/json/SearchMediaAssetsItemSAXParserJson:assetInfo	Lcom/starcor/core/domain/AssetCategoryCountStruct;
    //   823: putfield 115	com/starcor/core/domain/SearchStruct:asset_category_count	Lcom/starcor/core/domain/AssetCategoryCountStruct;
    //   826: goto -642 -> 184
    //   829: astore_2
    //   830: aload_2
    //   831: invokevirtual 239	java/lang/Exception:printStackTrace	()V
    //   834: aload_0
    //   835: getfield 26	com/starcor/core/parser/json/SearchMediaAssetsItemSAXParserJson:sInfo	Lcom/starcor/core/domain/SearchStruct;
    //   838: areturn
    //   839: astore 8
    //   841: aload 8
    //   843: invokevirtual 239	java/lang/Exception:printStackTrace	()V
    //   846: aload_0
    //   847: getfield 131	com/starcor/core/parser/json/SearchMediaAssetsItemSAXParserJson:fItem	Lcom/starcor/core/domain/SearchListItem;
    //   850: ldc 241
    //   852: putfield 150	com/starcor/core/domain/SearchListItem:serial_id	Ljava/lang/String;
    //   855: goto -549 -> 306
    //   858: astore 9
    //   860: aload 9
    //   862: invokevirtual 239	java/lang/Exception:printStackTrace	()V
    //   865: aload_0
    //   866: getfield 131	com/starcor/core/parser/json/SearchMediaAssetsItemSAXParserJson:fItem	Lcom/starcor/core/domain/SearchListItem;
    //   869: iconst_m1
    //   870: putfield 177	com/starcor/core/domain/SearchListItem:video_type	I
    //   873: goto -417 -> 456
    //   876: astore 10
    //   878: aload 10
    //   880: invokevirtual 239	java/lang/Exception:printStackTrace	()V
    //   883: aload_0
    //   884: getfield 131	com/starcor/core/parser/json/SearchMediaAssetsItemSAXParserJson:fItem	Lcom/starcor/core/domain/SearchListItem;
    //   887: iconst_0
    //   888: putfield 181	com/starcor/core/domain/SearchListItem:ui_style	I
    //   891: goto -405 -> 486
    //   894: astore 11
    //   896: aload 11
    //   898: invokevirtual 239	java/lang/Exception:printStackTrace	()V
    //   901: aload_0
    //   902: getfield 131	com/starcor/core/parser/json/SearchMediaAssetsItemSAXParserJson:fItem	Lcom/starcor/core/domain/SearchListItem;
    //   905: iconst_0
    //   906: putfield 185	com/starcor/core/domain/SearchListItem:play_count	I
    //   909: goto -393 -> 516
    //   912: astore 12
    //   914: aload 12
    //   916: invokevirtual 239	java/lang/Exception:printStackTrace	()V
    //   919: aload_0
    //   920: getfield 131	com/starcor/core/parser/json/SearchMediaAssetsItemSAXParserJson:fItem	Lcom/starcor/core/domain/SearchListItem;
    //   923: iconst_0
    //   924: putfield 198	com/starcor/core/domain/SearchListItem:user_score	I
    //   927: goto -376 -> 551
    //   930: astore 13
    //   932: aload 13
    //   934: invokevirtual 239	java/lang/Exception:printStackTrace	()V
    //   937: aload_0
    //   938: getfield 131	com/starcor/core/parser/json/SearchMediaAssetsItemSAXParserJson:fItem	Lcom/starcor/core/domain/SearchListItem;
    //   941: iconst_0
    //   942: putfield 202	com/starcor/core/domain/SearchListItem:point	I
    //   945: goto -364 -> 581
    //   948: astore 14
    //   950: aload 14
    //   952: invokevirtual 239	java/lang/Exception:printStackTrace	()V
    //   955: aload_0
    //   956: getfield 131	com/starcor/core/parser/json/SearchMediaAssetsItemSAXParserJson:fItem	Lcom/starcor/core/domain/SearchListItem;
    //   959: iconst_0
    //   960: putfield 215	com/starcor/core/domain/SearchListItem:billing	I
    //   963: goto -304 -> 659
    //
    // Exception table:
    //   from	to	target	type
    //   60	119	800	java/lang/Exception
    //   119	143	800	java/lang/Exception
    //   143	173	800	java/lang/Exception
    //   173	184	800	java/lang/Exception
    //   6	60	829	java/lang/Exception
    //   184	201	829	java/lang/Exception
    //   204	258	829	java/lang/Exception
    //   258	282	829	java/lang/Exception
    //   306	330	829	java/lang/Exception
    //   330	354	829	java/lang/Exception
    //   354	378	829	java/lang/Exception
    //   378	402	829	java/lang/Exception
    //   402	426	829	java/lang/Exception
    //   581	605	829	java/lang/Exception
    //   605	629	829	java/lang/Exception
    //   659	683	829	java/lang/Exception
    //   683	707	829	java/lang/Exception
    //   707	731	829	java/lang/Exception
    //   731	755	829	java/lang/Exception
    //   755	779	829	java/lang/Exception
    //   779	794	829	java/lang/Exception
    //   802	826	829	java/lang/Exception
    //   841	855	829	java/lang/Exception
    //   860	873	829	java/lang/Exception
    //   878	891	829	java/lang/Exception
    //   896	909	829	java/lang/Exception
    //   914	927	829	java/lang/Exception
    //   932	945	829	java/lang/Exception
    //   950	963	829	java/lang/Exception
    //   282	306	839	java/lang/Exception
    //   426	456	858	java/lang/Exception
    //   456	486	876	java/lang/Exception
    //   486	516	894	java/lang/Exception
    //   516	551	912	java/lang/Exception
    //   551	581	930	java/lang/Exception
    //   629	659	948	java/lang/Exception
  }
}

/* Location:           C:\Users\THX\Desktop\aa\aa\反编译工具包\out\classes_dex2jar.jar
 * Qualified Name:     com.starcor.core.parser.json.SearchMediaAssetsItemSAXParserJson
 * JD-Core Version:    0.6.2
 */