package com.sohu.mma.tracking.c;

public class k
{
  // ERROR //
  public static com.sohu.mma.tracking.b.g a(java.io.InputStream paramInputStream)
  {
    // Byte code:
    //   0: invokestatic 14	android/util/Xml:newPullParser	()Lorg/xmlpull/v1/XmlPullParser;
    //   3: astore 4
    //   5: aload 4
    //   7: aload_0
    //   8: ldc 16
    //   10: invokeinterface 22 3 0
    //   15: aload 4
    //   17: invokeinterface 26 1 0
    //   22: istore 5
    //   24: iload 5
    //   26: istore 6
    //   28: aconst_null
    //   29: astore 7
    //   31: aconst_null
    //   32: astore 8
    //   34: aconst_null
    //   35: astore 9
    //   37: aconst_null
    //   38: astore_3
    //   39: iload 6
    //   41: iconst_1
    //   42: if_icmpne +5 -> 47
    //   45: aload_3
    //   46: areturn
    //   47: iload 6
    //   49: tableswitch	default:+31 -> 80, 0:+61->110, 1:+31->80, 2:+85->134, 3:+997->1046
    //   81: lconst_0
    //   82: astore 12
    //   84: aload_3
    //   85: astore 13
    //   87: aload 4
    //   89: invokeinterface 29 1 0
    //   94: istore 15
    //   96: aload 13
    //   98: astore_3
    //   99: aload 12
    //   101: astore 9
    //   103: iload 15
    //   105: istore 6
    //   107: goto -68 -> 39
    //   110: new 31	com/sohu/mma/tracking/b/g
    //   113: dup
    //   114: invokespecial 35	com/sohu/mma/tracking/b/g:<init>	()V
    //   117: astore 25
    //   119: aload 9
    //   121: astore 26
    //   123: aload 25
    //   125: astore 13
    //   127: aload 26
    //   129: astore 12
    //   131: goto -44 -> 87
    //   134: aload 4
    //   136: invokeinterface 39 1 0
    //   141: astore 18
    //   143: ldc 41
    //   145: aload 18
    //   147: invokevirtual 47	java/lang/String:equals	(Ljava/lang/Object;)Z
    //   150: ifeq +14 -> 164
    //   153: aload_3
    //   154: new 49	com/sohu/mma/tracking/b/f
    //   157: dup
    //   158: invokespecial 50	com/sohu/mma/tracking/b/f:<init>	()V
    //   161: putfield 53	com/sohu/mma/tracking/b/g:a	Lcom/sohu/mma/tracking/b/f;
    //   164: aload_3
    //   165: getfield 53	com/sohu/mma/tracking/b/g:a	Lcom/sohu/mma/tracking/b/f;
    //   168: ifnull +75 -> 243
    //   171: ldc 55
    //   173: aload 18
    //   175: invokevirtual 47	java/lang/String:equals	(Ljava/lang/Object;)Z
    //   178: ifeq +17 -> 195
    //   181: aload_3
    //   182: getfield 53	com/sohu/mma/tracking/b/g:a	Lcom/sohu/mma/tracking/b/f;
    //   185: aload 4
    //   187: invokeinterface 58 1 0
    //   192: putfield 61	com/sohu/mma/tracking/b/f:a	Ljava/lang/String;
    //   195: ldc 63
    //   197: aload 18
    //   199: invokevirtual 47	java/lang/String:equals	(Ljava/lang/Object;)Z
    //   202: ifeq +17 -> 219
    //   205: aload_3
    //   206: getfield 53	com/sohu/mma/tracking/b/g:a	Lcom/sohu/mma/tracking/b/f;
    //   209: aload 4
    //   211: invokeinterface 58 1 0
    //   216: putfield 66	com/sohu/mma/tracking/b/f:b	Ljava/lang/String;
    //   219: ldc 68
    //   221: aload 18
    //   223: invokevirtual 47	java/lang/String:equals	(Ljava/lang/Object;)Z
    //   226: ifeq +17 -> 243
    //   229: aload_3
    //   230: getfield 53	com/sohu/mma/tracking/b/g:a	Lcom/sohu/mma/tracking/b/f;
    //   233: aload 4
    //   235: invokeinterface 58 1 0
    //   240: putfield 71	com/sohu/mma/tracking/b/f:c	Ljava/lang/String;
    //   243: ldc 73
    //   245: aload 18
    //   247: invokevirtual 47	java/lang/String:equals	(Ljava/lang/Object;)Z
    //   250: ifeq +14 -> 264
    //   253: aload_3
    //   254: new 75	java/util/ArrayList
    //   257: dup
    //   258: invokespecial 76	java/util/ArrayList:<init>	()V
    //   261: putfield 79	com/sohu/mma/tracking/b/g:b	Ljava/util/List;
    //   264: aload_3
    //   265: getfield 79	com/sohu/mma/tracking/b/g:b	Ljava/util/List;
    //   268: ifnull +967 -> 1235
    //   271: ldc 81
    //   273: aload 18
    //   275: invokevirtual 47	java/lang/String:equals	(Ljava/lang/Object;)Z
    //   278: ifeq +957 -> 1235
    //   281: new 83	com/sohu/mma/tracking/b/b
    //   284: dup
    //   285: invokespecial 84	com/sohu/mma/tracking/b/b:<init>	()V
    //   288: astore 19
    //   290: aload 19
    //   292: ifnull +929 -> 1221
    //   295: ldc 86
    //   297: aload 18
    //   299: invokevirtual 47	java/lang/String:equals	(Ljava/lang/Object;)Z
    //   302: ifeq +23 -> 325
    //   305: aload 19
    //   307: getfield 87	com/sohu/mma/tracking/b/b:a	Ljava/lang/String;
    //   310: ifnonnull +15 -> 325
    //   313: aload 19
    //   315: aload 4
    //   317: invokeinterface 58 1 0
    //   322: putfield 87	com/sohu/mma/tracking/b/b:a	Ljava/lang/String;
    //   325: ldc 89
    //   327: aload 18
    //   329: invokevirtual 47	java/lang/String:equals	(Ljava/lang/Object;)Z
    //   332: ifeq +15 -> 347
    //   335: aload 19
    //   337: new 91	com/sohu/mma/tracking/b/d
    //   340: dup
    //   341: invokespecial 92	com/sohu/mma/tracking/b/d:<init>	()V
    //   344: putfield 95	com/sohu/mma/tracking/b/b:b	Lcom/sohu/mma/tracking/b/d;
    //   347: aload 19
    //   349: getfield 95	com/sohu/mma/tracking/b/b:b	Lcom/sohu/mma/tracking/b/d;
    //   352: ifnull +28 -> 380
    //   355: ldc 97
    //   357: aload 18
    //   359: invokevirtual 47	java/lang/String:equals	(Ljava/lang/Object;)Z
    //   362: ifeq +18 -> 380
    //   365: aload 19
    //   367: getfield 95	com/sohu/mma/tracking/b/b:b	Lcom/sohu/mma/tracking/b/d;
    //   370: aload 4
    //   372: invokeinterface 58 1 0
    //   377: putfield 98	com/sohu/mma/tracking/b/d:a	Ljava/lang/String;
    //   380: ldc 100
    //   382: aload 18
    //   384: invokevirtual 47	java/lang/String:equals	(Ljava/lang/Object;)Z
    //   387: ifeq +15 -> 402
    //   390: aload 19
    //   392: new 102	com/sohu/mma/tracking/b/i
    //   395: dup
    //   396: invokespecial 103	com/sohu/mma/tracking/b/i:<init>	()V
    //   399: putfield 106	com/sohu/mma/tracking/b/b:c	Lcom/sohu/mma/tracking/b/i;
    //   402: aload 19
    //   404: getfield 106	com/sohu/mma/tracking/b/b:c	Lcom/sohu/mma/tracking/b/i;
    //   407: ifnull +53 -> 460
    //   410: ldc 108
    //   412: aload 18
    //   414: invokevirtual 47	java/lang/String:equals	(Ljava/lang/Object;)Z
    //   417: ifeq +18 -> 435
    //   420: aload 19
    //   422: getfield 106	com/sohu/mma/tracking/b/b:c	Lcom/sohu/mma/tracking/b/i;
    //   425: aload 4
    //   427: invokeinterface 58 1 0
    //   432: putfield 109	com/sohu/mma/tracking/b/i:a	Ljava/lang/String;
    //   435: ldc 111
    //   437: aload 18
    //   439: invokevirtual 47	java/lang/String:equals	(Ljava/lang/Object;)Z
    //   442: ifeq +18 -> 460
    //   445: aload 19
    //   447: getfield 106	com/sohu/mma/tracking/b/b:c	Lcom/sohu/mma/tracking/b/i;
    //   450: aload 4
    //   452: invokeinterface 58 1 0
    //   457: putfield 112	com/sohu/mma/tracking/b/i:b	Ljava/lang/String;
    //   460: ldc 114
    //   462: aload 18
    //   464: invokevirtual 47	java/lang/String:equals	(Ljava/lang/Object;)Z
    //   467: ifeq +15 -> 482
    //   470: aload 19
    //   472: new 116	com/sohu/mma/tracking/b/j
    //   475: dup
    //   476: invokespecial 117	com/sohu/mma/tracking/b/j:<init>	()V
    //   479: putfield 121	com/sohu/mma/tracking/b/b:d	Lcom/sohu/mma/tracking/b/j;
    //   482: aload 19
    //   484: getfield 121	com/sohu/mma/tracking/b/b:d	Lcom/sohu/mma/tracking/b/j;
    //   487: ifnull +155 -> 642
    //   490: ldc 123
    //   492: aload 18
    //   494: invokevirtual 47	java/lang/String:equals	(Ljava/lang/Object;)Z
    //   497: ifeq +21 -> 518
    //   500: aload 19
    //   502: getfield 121	com/sohu/mma/tracking/b/b:d	Lcom/sohu/mma/tracking/b/j;
    //   505: aload 4
    //   507: invokeinterface 58 1 0
    //   512: invokestatic 129	java/lang/Boolean:parseBoolean	(Ljava/lang/String;)Z
    //   515: putfield 132	com/sohu/mma/tracking/b/j:a	Z
    //   518: ldc 134
    //   520: aload 18
    //   522: invokevirtual 47	java/lang/String:equals	(Ljava/lang/Object;)Z
    //   525: ifeq +18 -> 543
    //   528: aload 19
    //   530: getfield 121	com/sohu/mma/tracking/b/b:d	Lcom/sohu/mma/tracking/b/j;
    //   533: aload 4
    //   535: invokeinterface 58 1 0
    //   540: putfield 135	com/sohu/mma/tracking/b/j:b	Ljava/lang/String;
    //   543: ldc 137
    //   545: aload 18
    //   547: invokevirtual 47	java/lang/String:equals	(Ljava/lang/Object;)Z
    //   550: ifeq +18 -> 568
    //   553: aload 19
    //   555: getfield 121	com/sohu/mma/tracking/b/b:d	Lcom/sohu/mma/tracking/b/j;
    //   558: new 139	java/util/HashMap
    //   561: dup
    //   562: invokespecial 140	java/util/HashMap:<init>	()V
    //   565: putfield 143	com/sohu/mma/tracking/b/j:c	Ljava/util/Map;
    //   568: aload 19
    //   570: getfield 121	com/sohu/mma/tracking/b/b:d	Lcom/sohu/mma/tracking/b/j;
    //   573: getfield 143	com/sohu/mma/tracking/b/j:c	Ljava/util/Map;
    //   576: ifnull +66 -> 642
    //   579: ldc 145
    //   581: aload 18
    //   583: invokevirtual 47	java/lang/String:equals	(Ljava/lang/Object;)Z
    //   586: ifne +33 -> 619
    //   589: ldc 147
    //   591: aload 18
    //   593: invokevirtual 47	java/lang/String:equals	(Ljava/lang/Object;)Z
    //   596: ifne +23 -> 619
    //   599: ldc 149
    //   601: aload 18
    //   603: invokevirtual 47	java/lang/String:equals	(Ljava/lang/Object;)Z
    //   606: ifne +13 -> 619
    //   609: ldc 151
    //   611: aload 18
    //   613: invokevirtual 47	java/lang/String:equals	(Ljava/lang/Object;)Z
    //   616: ifeq +26 -> 642
    //   619: aload 19
    //   621: getfield 121	com/sohu/mma/tracking/b/b:d	Lcom/sohu/mma/tracking/b/j;
    //   624: getfield 143	com/sohu/mma/tracking/b/j:c	Ljava/util/Map;
    //   627: aload 18
    //   629: aload 4
    //   631: invokeinterface 58 1 0
    //   636: invokeinterface 157 3 0
    //   641: pop
    //   642: ldc 159
    //   644: aload 18
    //   646: invokevirtual 47	java/lang/String:equals	(Ljava/lang/Object;)Z
    //   649: ifeq +15 -> 664
    //   652: aload 19
    //   654: new 161	com/sohu/mma/tracking/b/c
    //   657: dup
    //   658: invokespecial 162	com/sohu/mma/tracking/b/c:<init>	()V
    //   661: putfield 166	com/sohu/mma/tracking/b/b:e	Lcom/sohu/mma/tracking/b/c;
    //   664: aload 19
    //   666: getfield 166	com/sohu/mma/tracking/b/b:e	Lcom/sohu/mma/tracking/b/c;
    //   669: ifnull +541 -> 1210
    //   672: ldc 168
    //   674: aload 18
    //   676: invokevirtual 47	java/lang/String:equals	(Ljava/lang/Object;)Z
    //   679: ifeq +18 -> 697
    //   682: aload 19
    //   684: getfield 166	com/sohu/mma/tracking/b/b:e	Lcom/sohu/mma/tracking/b/c;
    //   687: new 75	java/util/ArrayList
    //   690: dup
    //   691: invokespecial 76	java/util/ArrayList:<init>	()V
    //   694: putfield 170	com/sohu/mma/tracking/b/c:a	Ljava/util/List;
    //   697: aload 19
    //   699: getfield 166	com/sohu/mma/tracking/b/b:e	Lcom/sohu/mma/tracking/b/c;
    //   702: getfield 170	com/sohu/mma/tracking/b/c:a	Ljava/util/List;
    //   705: ifnull +498 -> 1203
    //   708: ldc 172
    //   710: aload 18
    //   712: invokevirtual 47	java/lang/String:equals	(Ljava/lang/Object;)Z
    //   715: ifeq +488 -> 1203
    //   718: new 174	com/sohu/mma/tracking/b/a
    //   721: dup
    //   722: invokespecial 175	com/sohu/mma/tracking/b/a:<init>	()V
    //   725: astore 20
    //   727: aload 20
    //   729: ifnull +97 -> 826
    //   732: ldc 177
    //   734: aload 18
    //   736: invokevirtual 47	java/lang/String:equals	(Ljava/lang/Object;)Z
    //   739: ifeq +15 -> 754
    //   742: aload 20
    //   744: aload 4
    //   746: invokeinterface 58 1 0
    //   751: putfield 178	com/sohu/mma/tracking/b/a:a	Ljava/lang/String;
    //   754: ldc 180
    //   756: aload 18
    //   758: invokevirtual 47	java/lang/String:equals	(Ljava/lang/Object;)Z
    //   761: ifeq +15 -> 776
    //   764: aload 20
    //   766: aload 4
    //   768: invokeinterface 58 1 0
    //   773: putfield 181	com/sohu/mma/tracking/b/a:b	Ljava/lang/String;
    //   776: ldc 183
    //   778: aload 18
    //   780: invokevirtual 47	java/lang/String:equals	(Ljava/lang/Object;)Z
    //   783: ifeq +18 -> 801
    //   786: aload 20
    //   788: aload 4
    //   790: invokeinterface 58 1 0
    //   795: invokestatic 129	java/lang/Boolean:parseBoolean	(Ljava/lang/String;)Z
    //   798: putfield 185	com/sohu/mma/tracking/b/a:c	Z
    //   801: ldc 187
    //   803: aload 18
    //   805: invokevirtual 47	java/lang/String:equals	(Ljava/lang/Object;)Z
    //   808: ifeq +18 -> 826
    //   811: aload 20
    //   813: aload 4
    //   815: invokeinterface 58 1 0
    //   820: invokestatic 129	java/lang/Boolean:parseBoolean	(Ljava/lang/String;)Z
    //   823: putfield 189	com/sohu/mma/tracking/b/a:d	Z
    //   826: ldc 191
    //   828: aload 18
    //   830: invokevirtual 47	java/lang/String:equals	(Ljava/lang/Object;)Z
    //   833: ifeq +18 -> 851
    //   836: aload 19
    //   838: getfield 166	com/sohu/mma/tracking/b/b:e	Lcom/sohu/mma/tracking/b/c;
    //   841: new 75	java/util/ArrayList
    //   844: dup
    //   845: invokespecial 76	java/util/ArrayList:<init>	()V
    //   848: putfield 192	com/sohu/mma/tracking/b/c:b	Ljava/util/List;
    //   851: aload 19
    //   853: getfield 166	com/sohu/mma/tracking/b/b:e	Lcom/sohu/mma/tracking/b/c;
    //   856: getfield 192	com/sohu/mma/tracking/b/c:b	Ljava/util/List;
    //   859: ifnull +337 -> 1196
    //   862: ldc 194
    //   864: aload 18
    //   866: invokevirtual 47	java/lang/String:equals	(Ljava/lang/Object;)Z
    //   869: ifeq +327 -> 1196
    //   872: new 196	com/sohu/mma/tracking/b/e
    //   875: dup
    //   876: invokespecial 197	com/sohu/mma/tracking/b/e:<init>	()V
    //   879: astore 21
    //   881: aload 21
    //   883: ifnull +72 -> 955
    //   886: ldc 177
    //   888: aload 18
    //   890: invokevirtual 47	java/lang/String:equals	(Ljava/lang/Object;)Z
    //   893: ifeq +15 -> 908
    //   896: aload 21
    //   898: aload 4
    //   900: invokeinterface 58 1 0
    //   905: putfield 198	com/sohu/mma/tracking/b/e:a	Ljava/lang/String;
    //   908: ldc 180
    //   910: aload 18
    //   912: invokevirtual 47	java/lang/String:equals	(Ljava/lang/Object;)Z
    //   915: ifeq +15 -> 930
    //   918: aload 21
    //   920: aload 4
    //   922: invokeinterface 58 1 0
    //   927: putfield 199	com/sohu/mma/tracking/b/e:b	Ljava/lang/String;
    //   930: ldc 183
    //   932: aload 18
    //   934: invokevirtual 47	java/lang/String:equals	(Ljava/lang/Object;)Z
    //   937: ifeq +18 -> 955
    //   940: aload 21
    //   942: aload 4
    //   944: invokeinterface 58 1 0
    //   949: invokestatic 129	java/lang/Boolean:parseBoolean	(Ljava/lang/String;)Z
    //   952: putfield 200	com/sohu/mma/tracking/b/e:c	Z
    //   955: ldc 202
    //   957: aload 18
    //   959: invokevirtual 47	java/lang/String:equals	(Ljava/lang/Object;)Z
    //   962: ifeq +15 -> 977
    //   965: aload 19
    //   967: aload 4
    //   969: invokeinterface 58 1 0
    //   974: putfield 205	com/sohu/mma/tracking/b/b:f	Ljava/lang/String;
    //   977: ldc 207
    //   979: aload 18
    //   981: invokevirtual 47	java/lang/String:equals	(Ljava/lang/Object;)Z
    //   984: ifeq +15 -> 999
    //   987: aload 19
    //   989: aload 4
    //   991: invokeinterface 58 1 0
    //   996: putfield 210	com/sohu/mma/tracking/b/b:g	Ljava/lang/String;
    //   999: ldc 212
    //   1001: aload 18
    //   1003: invokevirtual 47	java/lang/String:equals	(Ljava/lang/Object;)Z
    //   1006: ifeq +168 -> 1174
    //   1009: aload 19
    //   1011: aload 4
    //   1013: invokeinterface 58 1 0
    //   1018: invokestatic 129	java/lang/Boolean:parseBoolean	(Ljava/lang/String;)Z
    //   1021: putfield 215	com/sohu/mma/tracking/b/b:h	Z
    //   1024: aload 21
    //   1026: astore 7
    //   1028: aload_3
    //   1029: astore 13
    //   1031: aload 20
    //   1033: astore 23
    //   1035: aload 19
    //   1037: astore 8
    //   1039: aload 23
    //   1041: astore 12
    //   1043: goto -956 -> 87
    //   1046: aload 4
    //   1048: invokeinterface 39 1 0
    //   1053: astore 10
    //   1055: ldc 81
    //   1057: aload 10
    //   1059: invokevirtual 47	java/lang/String:equals	(Ljava/lang/Object;)Z
    //   1062: ifeq +18 -> 1080
    //   1065: aload_3
    //   1066: getfield 79	com/sohu/mma/tracking/b/g:b	Ljava/util/List;
    //   1069: aload 8
    //   1071: invokeinterface 220 2 0
    //   1076: pop
    //   1077: aconst_null
    //   1078: astore 8
    //   1080: ldc 172
    //   1082: aload 10
    //   1084: invokevirtual 47	java/lang/String:equals	(Ljava/lang/Object;)Z
    //   1087: ifeq +22 -> 1109
    //   1090: aload 8
    //   1092: getfield 166	com/sohu/mma/tracking/b/b:e	Lcom/sohu/mma/tracking/b/c;
    //   1095: getfield 170	com/sohu/mma/tracking/b/c:a	Ljava/util/List;
    //   1098: aload 9
    //   1100: invokeinterface 220 2 0
    //   1105: pop
    //   1106: aconst_null
    //   1107: astore 9
    //   1109: ldc 194
    //   1111: aload 10
    //   1113: invokevirtual 47	java/lang/String:equals	(Ljava/lang/Object;)Z
    //   1116: ifeq -1036 -> 80
    //   1119: aload 8
    //   1121: getfield 166	com/sohu/mma/tracking/b/b:e	Lcom/sohu/mma/tracking/b/c;
    //   1124: getfield 192	com/sohu/mma/tracking/b/c:b	Ljava/util/List;
    //   1127: aload 7
    //   1129: invokeinterface 220 2 0
    //   1134: pop
    //   1135: aload 9
    //   1137: astore 12
    //   1139: aload_3
    //   1140: astore 13
    //   1142: aconst_null
    //   1143: astore 7
    //   1145: goto -1058 -> 87
    //   1148: astore_1
    //   1149: aload_1
    //   1150: astore_2
    //   1151: aconst_null
    //   1152: astore_3
    //   1153: aload_2
    //   1154: invokevirtual 223	java/lang/Exception:printStackTrace	()V
    //   1157: aload_3
    //   1158: areturn
    //   1159: astore 14
    //   1161: aload 13
    //   1163: astore_3
    //   1164: aload 14
    //   1166: astore_2
    //   1167: goto -14 -> 1153
    //   1170: astore_2
    //   1171: goto -18 -> 1153
    //   1174: aload 21
    //   1176: astore 7
    //   1178: aload_3
    //   1179: astore 13
    //   1181: aload 20
    //   1183: astore 22
    //   1185: aload 19
    //   1187: astore 8
    //   1189: aload 22
    //   1191: astore 12
    //   1193: goto -1106 -> 87
    //   1196: aload 7
    //   1198: astore 21
    //   1200: goto -319 -> 881
    //   1203: aload 9
    //   1205: astore 20
    //   1207: goto -480 -> 727
    //   1210: aload 9
    //   1212: astore 20
    //   1214: aload 7
    //   1216: astore 21
    //   1218: goto -263 -> 955
    //   1221: aload 19
    //   1223: astore 8
    //   1225: aload 9
    //   1227: astore 12
    //   1229: aload_3
    //   1230: astore 13
    //   1232: goto -1145 -> 87
    //   1235: aload 8
    //   1237: astore 19
    //   1239: goto -949 -> 290
    //
    // Exception table:
    //   from	to	target	type
    //   0	24	1148	java/lang/Exception
    //   87	96	1159	java/lang/Exception
    //   110	119	1170	java/lang/Exception
    //   134	164	1170	java/lang/Exception
    //   164	195	1170	java/lang/Exception
    //   195	219	1170	java/lang/Exception
    //   219	243	1170	java/lang/Exception
    //   243	264	1170	java/lang/Exception
    //   264	290	1170	java/lang/Exception
    //   295	325	1170	java/lang/Exception
    //   325	347	1170	java/lang/Exception
    //   347	380	1170	java/lang/Exception
    //   380	402	1170	java/lang/Exception
    //   402	435	1170	java/lang/Exception
    //   435	460	1170	java/lang/Exception
    //   460	482	1170	java/lang/Exception
    //   482	518	1170	java/lang/Exception
    //   518	543	1170	java/lang/Exception
    //   543	568	1170	java/lang/Exception
    //   568	619	1170	java/lang/Exception
    //   619	642	1170	java/lang/Exception
    //   642	664	1170	java/lang/Exception
    //   664	697	1170	java/lang/Exception
    //   697	727	1170	java/lang/Exception
    //   732	754	1170	java/lang/Exception
    //   754	776	1170	java/lang/Exception
    //   776	801	1170	java/lang/Exception
    //   801	826	1170	java/lang/Exception
    //   826	851	1170	java/lang/Exception
    //   851	881	1170	java/lang/Exception
    //   886	908	1170	java/lang/Exception
    //   908	930	1170	java/lang/Exception
    //   930	955	1170	java/lang/Exception
    //   955	977	1170	java/lang/Exception
    //   977	999	1170	java/lang/Exception
    //   999	1024	1170	java/lang/Exception
    //   1046	1077	1170	java/lang/Exception
    //   1080	1106	1170	java/lang/Exception
    //   1109	1135	1170	java/lang/Exception
  }
}

/* Location:           C:\Users\THX\Desktop\aa\aa\反编译工具包\out\classes_dex2jar.jar
 * Qualified Name:     com.sohu.mma.tracking.c.k
 * JD-Core Version:    0.6.2
 */